Workbook

Sheet LEIA-ME
B2: Análise Crítica · TIROL
B3: Dados fictícios: construtora inventada de Natal/RN, portfólio Vizu Dados.
B4: Uma aba por mês (MMMAA). Os campos são lidos pelo rótulo da coluna B.
B5: Versão 01 da planilha: a dívida da obra (item 10) desconta do resultado.

Sheet FEV26
B2: ANÁLISE DE DESEMPENHO ECONÔMICO DA OBRA
B3: Construtora fictícia de Natal/RN · portfólio Vizu Dados · dados inventados
B4: Versão 01 · revisão de 01/09/2025: a dívida da obra passa a descontar do resultado
B18: Célula editável
B19: Resultado (não editar)
B20: Tabela anexada
B21: % relacionada
B24: 1º passo: Projeto (definir o empreendimento) | D24: TIROL
B26: 2º passo: Mês de análise (definir o mês de referência) | E26: 46054
B28: 3º passo: Orçamento da obra projetado (com INCC no a realizar) | J28: 30119500
B29: Tipo do orçamento | J29: Orçamento legal
B31: 4º passo: Previsto do mês (incluir o % do cronograma) | F31: 0.0025
B33: 5º passo: Executado do mês (incluir o % medido) | F33: 0.0014
B35: 6º passo: Previsto acumulado do mês | F35: 0.0025
B37: 7º passo: Executado acumulado do mês | F37: 0.0014
B39: 8º passo: Crédito do orçamento (executado acumulado × orçamento) | F39: =F37*J28 -> 42167.3
B41: 8º passo (cont.): Saldo de contrato (tabela) | F41: =E74 -> 0
B43: 9º passo: Adiantamento de serviços não medidos (tabela) | F43: =E88 -> 0
B45: 10º passo: Adiantamento de materiais não estocados (tabela) | F45: =J74 -> 0
B47: 11º passo: Estoque de materiais (almoxarifado) | F47: =J88 -> 30119.5
B49: 12º passo: Equipamentos comprados (valor de mercado) | F49: =E102 -> 76300
B51: 13º passo: Receitas de personalizações (tabela) | F51: =J102 -> 0
B53: 14º passo: Contas a pagar dos medidos (relatório a pagar) | F53: =E115 -> 20000
B55: 15º passo: Valor desembolsado pela obra (relatório conferido) | F55: 51869.3
B56: Valor corrigido (sem os itens apontados irregularmente) | F56: =F55-J115 -> 51869.3
B58: 16º passo: Dívida da obra a ser paga (outra obra da carteira) | F58: =E129 -> 0
B63: Saldo de contrato | G63: Adiantamento de materiais não estocados
B74: Total | E74: =SUM(E64:E73) -> 0 | G74: Total | J74: =SUM(J64:J73) -> 0
B77: Adiantamento de serviços não medidos | G77: Estoque de materiais
G78: Material de canteiro (tapumes e contêineres) | J78: 10970.74
G79: Cimento e agregados | J79: 6700.22
G80: Aço CA-50 para fundação | J80: 12448.54
B88: Total | E88: =SUM(E78:E87) -> 0 | G88: Total | J88: =SUM(J78:J87) -> 30119.5
B91: Equipamentos comprados | G91: Receitas de personalizações
B92: Betoneira 400 L | E92: 9800
B93: Guincho de coluna | E93: 38500
B94: Container escritório (2 un.) | E94: 28000
B102: Total | E102: =SUM(E92:E101) -> 76300 | G102: Total | J102: =SUM(J92:J101) -> 0
B105: Contas a pagar dos medidos | G105: Itens apontados irregularmente no relatório
B106: Medição de terraplenagem · NF 12007 | E106: 5769.67
B107: Locação de equipamentos · NF 32241 | E107: 6314.98
B108: Encargos e INSS do mês · NF 71223 | E108: 7915.35
B115: Total | E115: =SUM(E106:E114) -> 20000 | G115: Total | J115: =SUM(J106:J114) -> 0
B118: Dívida da obra a ser paga
B129: Total | E129: =SUM(E119:E128) -> 0
B132: RESULTADO PARA UTILIZAR NA APRESENTAÇÃO
G135: Tabela informativa do desembolso do mês
C136: Projeto | D136: =D24 -> TIROL | G136: Valor previsto para o mês | J136: 49787.1
C137: Orçamento | D137: =J28 -> 30119500 | G137: Valor desembolsado no mês | J137: 51869.3
C138: Tipo do orçamento | D138: =J29 -> Orçamento legal | G138: Diferença entre o previsto e o desembolsado | J138: =J137-J136 -> 2082.2
C139: Mês | D139: =E26 -> 46054 | G139: Justificativa para diferença acima de 10% (obrigatória)
C140: % previsto do mês | D140: =F31 -> 0.0025
C141: % executado do mês | D141: =F33 -> 0.0014
C142: % previsto acumulado | D142: =F35 -> 0.0025
C143: % executado acumulado | D143: =F37 -> 0.0014
B145: 01 | C145: Crédito do orçamento | D145: =F39 -> 42167.3 | E145: =D145/$D$137 -> 0.0014
B146: 02 | C146: Saldo de contrato | D146: =F41 -> 0 | E146: =D146/$D$137 -> 0
B147: 03 | C147: Adiantamento de serviços não medidos | D147: =F43 -> 0 | E147: =D147/$D$137 -> 0
B148: 04 | C148: Adiantamento de materiais não estocados | D148: =F45 -> 0 | E148: =D148/$D$137 -> 0
B149: 05 | C149: Estoque de materiais | D149: =F47 -> 30119.5 | E149: =D149/$D$137 -> 0.001
B150: 06 | C150: Equipamentos (valor de mercado) | D150: =F49 -> 76300 | E150: =D150/$D$137 -> 0.0025332426
B151: 07 | C151: Receita de personalizações | D151: =F51 -> 0 | E151: =D151/$D$137 -> 0
B152: 08 | C152: Contas a pagar dos medidos | D152: =F53 -> 20000 | E152: =D152/$D$137 -> 0.00066402165
B153: 09 | C153: Valor desembolsado (corrigido) | D153: =F56 -> 51869.3 | E153: =D153/$D$137 -> 0.0017221169
B154: 10 | C154: Dívida da obra a ser paga | D154: =F58 -> 0 | E154: =D154/$D$137 -> 0
C155: Resultado mensal da obra | D155: =D145+D146+D147+D148+D149+D150+D151-D152-D153-D154 -> 76717.5 | E155: =D155/D137 -> 0.002547104
C156: Resultado do mês anterior
B160: Significado de cada item
B162: Crédito do orçamento:
B163: Quanto a obra podia ter gasto pelo que executou: orçamento × executado acumulado.
B164: Saldo de contrato:
B165: Desconto obtido num contrato e ainda não realizado; abatido à medida que o serviço é medido.
B166: Adiantamento de serviços não medidos:
B167: Sinal pago de contrato ainda não medido (ex.: elevadores).
B168: Adiantamento de materiais não estocados:
B169: Material pago que ainda não chegou à obra (ex.: esquadrias).
B170: Estoque de materiais:
B171: Material no almoxarifado, ainda não aplicado, informado pelo almoxarife.
B172: Equipamentos (valor de mercado):
... B181: Material de outra obra da carteira usado nesta: custo da obra, desconta do resultado (versão 01 da planilha).

Sheet MAR26
B2: ANÁLISE DE DESEMPENHO ECONÔMICO DA OBRA
B3: Construtora fictícia de Natal/RN · portfólio Vizu Dados · dados inventados
B4: Versão 01 · revisão de 01/09/2025: a dívida da obra passa a descontar do resultado
B18: Célula editável
B19: Resultado (não editar)
B20: Tabela anexada
B21: % relacionada
B24: 1º passo: Projeto (definir o empreendimento) | D24: TIROL
B26: 2º passo: Mês de análise (definir o mês de referência) | E26: 46082
B28: 3º passo: Orçamento da obra projetado (com INCC no a realizar) | J28: 30243400
B29: Tipo do orçamento | J29: Orçamento legal
B31: 4º passo: Previsto do mês (incluir o % do cronograma) | F31: 0.0075
B33: 5º passo: Executado do mês (incluir o % medido) | F33: 0.0043
B35: 6º passo: Previsto acumulado do mês | F35: 0.01
B37: 7º passo: Executado acumulado do mês | F37: 0.0057
B39: 8º passo: Crédito do orçamento (executado acumulado × orçamento) | F39: =F37*J28 -> 172387.38
B41: 8º passo (cont.): Saldo de contrato (tabela) | F41: =E74 -> 0
B43: 9º passo: Adiantamento de serviços não medidos (tabela) | F43: =E88 -> 0
B45: 10º passo: Adiantamento de materiais não estocados (tabela) | F45: =J74 -> 0
B47: 11º passo: Estoque de materiais (almoxarifado) | F47: =J88 -> 61094.2
B49: 12º passo: Equipamentos comprados (valor de mercado) | F49: =E102 -> 76300
B51: 13º passo: Receitas de personalizações (tabela) | F51: =J102 -> 0
B53: 14º passo: Contas a pagar dos medidos (relatório a pagar) | F53: =E115 -> 31554.1
B55: 15º passo: Valor desembolsado pela obra (relatório conferido) | F55: 200559.33
B56: Valor corrigido (sem os itens apontados irregularmente) | F56: =F55-J115 -> 200559.33
B58: 16º passo: Dívida da obra a ser paga (outra obra da carteira) | F58: =E129 -> 0
B63: Saldo de contrato | G63: Adiantamento de materiais não estocados
B74: Total | E74: =SUM(E64:E73) -> 0 | G74: Total | J74: =SUM(J64:J73) -> 0
B77: Adiantamento de serviços não medidos | G77: Estoque de materiais
G78: Material de canteiro (tapumes e contêineres) | J78: 22941.39
G79: Cimento e agregados | J79: 14685.39
G80: Aço CA-50 para fundação | J80: 23467.42
B88: Total | E88: =SUM(E78:E87) -> 0 | G88: Total | J88: =SUM(J78:J87) -> 61094.2
B91: Equipamentos comprados | G91: Receitas de personalizações
B92: Betoneira 400 L | E92: 9800
B93: Guincho de coluna | E93: 38500
B94: Container escritório (2 un.) | E94: 28000
B102: Total | E102: =SUM(E92:E101) -> 76300 | G102: Total | J102: =SUM(J92:J101) -> 0
B105: Contas a pagar dos medidos | G105: Itens apontados irregularmente no relatório
B106: Medição de terraplenagem · NF 77565 | E106: 7639.46
B107: Locação de equipamentos · NF 23137 | E107: 11570.25
B108: Encargos e INSS do mês · NF 30173 | E108: 12344.39
B115: Total | E115: =SUM(E106:E114) -> 31554.1 | G115: Total | J115: =SUM(J106:J114) -> 0
B118: Dívida da obra a ser paga
B129: Total | E129: =SUM(E119:E128) -> 0
B132: RESULTADO PARA UTILIZAR NA APRESENTAÇÃO
G135: Tabela informativa do desembolso do mês
C136: Projeto | D136: =D24 -> TIROL | G136: Valor previsto para o mês | J136: 146784.02
C137: Orçamento | D137: =J28 -> 30243400 | G137: Valor desembolsado no mês | J137: 148690.03
C138: Tipo do orçamento | D138: =J29 -> Orçamento legal | G138: Diferença entre o previsto e o desembolsado | J138: =J137-J136 -> 1906.01
C139: Mês | D139: =E26 -> 46082 | G139: Justificativa para diferença acima de 10% (obrigatória)
C140: % previsto do mês | D140: =F31 -> 0.0075
C141: % executado do mês | D141: =F33 -> 0.0043
C142: % previsto acumulado | D142: =F35 -> 0.01
C143: % executado acumulado | D143: =F37 -> 0.0057
B145: 01 | C145: Crédito do orçamento | D145: =F39 -> 172387.38 | E145: =D145/$D$137 -> 0.0057
B146: 02 | C146: Saldo de contrato | D146: =F41 -> 0 | E146: =D146/$D$137 -> 0
B147: 03 | C147: Adiantamento de serviços não medidos | D147: =F43 -> 0 | E147: =D147/$D$137 -> 0
B148: 04 | C148: Adiantamento de materiais não estocados | D148: =F45 -> 0 | E148: =D148/$D$137 -> 0
B149: 05 | C149: Estoque de materiais | D149: =F47 -> 61094.2 | E149: =D149/$D$137 -> 0.0020200837
B150: 06 | C150: Equipamentos (valor de mercado) | D150: =F49 -> 76300 | E150: =D150/$D$137 -> 0.0025228645
B151: 07 | C151: Receita de personalizações | D151: =F51 -> 0 | E151: =D151/$D$137 -> 0
B152: 08 | C152: Contas a pagar dos medidos | D152: =F53 -> 31554.1 | E152: =D152/$D$137 -> 0.0010433384
B153: 09 | C153: Valor desembolsado (corrigido) | D153: =F56 -> 200559.33 | E153: =D153/$D$137 -> 0.0066315074
B154: 10 | C154: Dívida da obra a ser paga | D154: =F58 -> 0 | E154: =D154/$D$137 -> 0
C155: Resultado mensal da obra | D155: =D145+D146+D147+D148+D149+D150+D151-D152-D153-D154 -> 77668.15 | E155: =D155/D137 -> 0.0025681025
C156: Resultado do mês anterior | D156: =FEV26!D155 -> 76717.5 | E156: =FEV26!E155 -> 0.002547104
B160: Significado de cada item
B162: Crédito do orçamento:
B163: Quanto a obra podia ter gasto pelo que executou: orçamento × executado acumulado.
B164: Saldo de contrato:
B165: Desconto obtido num contrato e ainda não realizado; abatido à medida que o serviço é medido.
B166: Adiantamento de serviços não medidos:
B167: Sinal pago de contrato ainda não medido (ex.: elevadores).
B168: Adiantamento de materiais não estocados:
B169: Material pago que ainda não chegou à obra (ex.: esquadrias).
B170: Estoque de materiais:
B171: Material no almoxarifado, ainda não aplicado, informado pelo almoxarife.
B172: Equipamentos (valor de mercado):
... B181: Material de outra obra da carteira usado nesta: custo da obra, desconta do resultado (versão 01 da planilha).

Sheet ABR26
B2: ANÁLISE DE DESEMPENHO ECONÔMICO DA OBRA
B3: Construtora fictícia de Natal/RN · portfólio Vizu Dados · dados inventados
B4: Versão 01 · revisão de 01/09/2025: a dívida da obra passa a descontar do resultado
B18: Célula editável
B19: Resultado (não editar)
B20: Tabela anexada
B21: % relacionada
B24: 1º passo: Projeto (definir o empreendimento) | D24: TIROL
B26: 2º passo: Mês de análise (definir o mês de referência) | E26: 46082
B28: 3º passo: Orçamento da obra projetado (com INCC no a realizar) | J28: 30367300
B29: Tipo do orçamento | J29: Orçamento legal
B31: 4º passo: Previsto do mês (incluir o % do cronograma) | F31: 0.012
B33: 5º passo: Executado do mês (incluir o % medido) | F33: 0.0057
B35: 6º passo: Previsto acumulado do mês | F35: 0.022
B37: 7º passo: Executado acumulado do mês | F37: 0.0114
B39: 8º passo: Crédito do orçamento (executado acumulado × orçamento) | F39: =F37*J28 -> 346187.22
B41: 8º passo (cont.): Saldo de contrato (tabela) | F41: =E74 -> 0
B43: 9º passo: Adiantamento de serviços não medidos (tabela) | F43: =E88 -> 0
B45: 10º passo: Adiantamento de materiais não estocados (tabela) | F45: =J74 -> 0
B47: 11º passo: Estoque de materiais (almoxarifado) | F47: =J88 -> 51092.5
B49: 12º passo: Equipamentos comprados (valor de mercado) | F49: =E102 -> 76300
B51: 13º passo: Receitas de personalizações (tabela) | F51: =J102 -> 0
B53: 14º passo: Contas a pagar dos medidos (relatório a pagar) | F53: =E115 -> 34905.3
B55: 15º passo: Valor desembolsado pela obra (relatório conferido) | F55: 360309.69
B56: Valor corrigido (sem os itens apontados irregularmente) | F56: =F55-J115 -> 360309.69
B58: 16º passo: Dívida da obra a ser paga (outra obra da carteira) | F58: =E129 -> 0
B63: Saldo de contrato | G63: Adiantamento de materiais não estocados
B74: Total | E74: =SUM(E64:E73) -> 0 | G74: Total | J74: =SUM(J64:J73) -> 0
B77: Adiantamento de serviços não medidos | G77: Estoque de materiais
G78: Material de canteiro (tapumes e contêineres) | J78: 14244.22
G79: Cimento e agregados | J79: 18308.45
G80: Aço CA-50 para fundação | J80: 18539.83
B88: Total | E88: =SUM(E78:E87) -> 0 | G88: Total | J88: =SUM(J78:J87) -> 51092.5
B91: Equipamentos comprados | G91: Receitas de personalizações
B92: Betoneira 400 L | E92: 9800
B93: Guincho de coluna | E93: 38500
B94: Container escritório (2 un.) | E94: 28000
B102: Total | E102: =SUM(E92:E101) -> 76300 | G102: Total | J102: =SUM(J92:J101) -> 0
B105: Contas a pagar dos medidos | G105: Itens apontados irregularmente no relatório
B106: Medição de terraplenagem · NF 73503 | E106: 9136.13
B107: Locação de equipamentos · NF 33254 | E107: 13895.9
B108: Encargos e INSS do mês · NF 74163 | E108: 11873.27
B115: Total | E115: =SUM(E106:E114) -> 34905.3 | G115: Total | J115: =SUM(J106:J114) -> 0
B118: Dívida da obra a ser paga
B129: Total | E129: =SUM(E119:E128) -> 0
B132: RESULTADO PARA UTILIZAR NA APRESENTAÇÃO
G135: Tabela informativa do desembolso do mês
C136: Projeto | D136: =D24 -> TIROL | G136: Valor previsto para o mês | J136: 169667.48
C137: Orçamento | D137: =J28 -> 30367300 | G137: Valor desembolsado no mês | J137: 159750.36
C138: Tipo do orçamento | D138: =J29 -> Orçamento legal | G138: Diferença entre o previsto e o desembolsado | J138: =J137-J136 -> -9917.12
C139: Mês | D139: =E26 -> 46082 | G139: Justificativa para diferença acima de 10% (obrigatória)
C140: % previsto do mês | D140: =F31 -> 0.012
C141: % executado do mês | D141: =F33 -> 0.0057
C142: % previsto acumulado | D142: =F35 -> 0.022
C143: % executado acumulado | D143: =F37 -> 0.0114
B145: 01 | C145: Crédito do orçamento | D145: =F39 -> 346187.22 | E145: =D145/$D$137 -> 0.0114
B146: 02 | C146: Saldo de contrato | D146: =F41 -> 0 | E146: =D146/$D$137 -> 0
B147: 03 | C147: Adiantamento de serviços não medidos | D147: =F43 -> 0 | E147: =D147/$D$137 -> 0
B148: 04 | C148: Adiantamento de materiais não estocados | D148: =F45 -> 0 | E148: =D148/$D$137 -> 0
B149: 05 | C149: Estoque de materiais | D149: =F47 -> 51092.5 | E149: =D149/$D$137 -> 0.0016824841
B150: 06 | C150: Equipamentos (valor de mercado) | D150: =F49 -> 76300 | E150: =D150/$D$137 -> 0.0025125711
B151: 07 | C151: Receita de personalizações | D151: =F51 -> 0 | E151: =D151/$D$137 -> 0
B152: 08 | C152: Contas a pagar dos medidos | D152: =F53 -> 34905.3 | E152: =D152/$D$137 -> 0.0011494371
B153: 09 | C153: Valor desembolsado (corrigido) | D153: =F56 -> 360309.69 | E153: =D153/$D$137 -> 0.011865055
B154: 10 | C154: Dívida da obra a ser paga | D154: =F58 -> 0 | E154: =D154/$D$137 -> 0
C155: Resultado mensal da obra | D155: =D145+D146+D147+D148+D149+D150+D151-D152-D153-D154 -> 78364.73 | E155: =D155/D137 -> 0.002580563
C156: Resultado do mês anterior | D156: =MAR26!D155 -> 77668.15 | E156: =MAR26!E155 -> 0.0025681025
B160: Significado de cada item
B162: Crédito do orçamento:
B163: Quanto a obra podia ter gasto pelo que executou: orçamento × executado acumulado.
B164: Saldo de contrato:
B165: Desconto obtido num contrato e ainda não realizado; abatido à medida que o serviço é medido.
B166: Adiantamento de serviços não medidos:
B167: Sinal pago de contrato ainda não medido (ex.: elevadores).
B168: Adiantamento de materiais não estocados:
B169: Material pago que ainda não chegou à obra (ex.: esquadrias).
B170: Estoque de materiais:
B171: Material no almoxarifado, ainda não aplicado, informado pelo almoxarife.
B172: Equipamentos (valor de mercado):
... B181: Material de outra obra da carteira usado nesta: custo da obra, desconta do resultado (versão 01 da planilha).

Sheet MAI26
B2: ANÁLISE DE DESEMPENHO ECONÔMICO DA OBRA
B3: Construtora fictícia de Natal/RN · portfólio Vizu Dados · dados inventados
B4: Versão 01 · revisão de 01/09/2025: a dívida da obra passa a descontar do resultado
B18: Célula editável
B19: Resultado (não editar)
B20: Tabela anexada
B21: % relacionada
B24: 1º passo: Projeto (definir o empreendimento) | D24: TIROL
B26: 2º passo: Mês de análise (definir o mês de referência) | E26: 46143
B28: 3º passo: Orçamento da obra projetado (com INCC no a realizar) | J28: 30491200
B29: Tipo do orçamento | J29: Orçamento legal
B31: 4º passo: Previsto do mês (incluir o % do cronograma) | F31: 0.0163
B33: 5º passo: Executado do mês (incluir o % medido) | F33: 0.0082
B35: 6º passo: Previsto acumulado do mês | F35: 0.0383
B37: 7º passo: Executado acumulado do mês | F37: 0.0196
B39: 8º passo: Crédito do orçamento (executado acumulado × orçamento) | F39: =F37*J28 -> 597627.52
B41: 8º passo (cont.): Saldo de contrato (tabela) | F41: =E74 -> 0
B43: 9º passo: Adiantamento de serviços não medidos (tabela) | F43: =E88 -> 0
B45: 10º passo: Adiantamento de materiais não estocados (tabela) | F45: =J74 -> 0
B47: 11º passo: Estoque de materiais (almoxarifado) | F47: =J88 -> 69381.89
B49: 12º passo: Equipamentos comprados (valor de mercado) | F49: =E102 -> 76300
B51: 13º passo: Receitas de personalizações (tabela) | F51: =J102 -> 0
B53: 14º passo: Contas a pagar dos medidos (relatório a pagar) | F53: =E115 -> 46452.66
B55: 15º passo: Valor desembolsado pela obra (relatório conferido) | F55: 618175.76
B56: Valor corrigido (sem os itens apontados irregularmente) | F56: =F55-J115 -> 618175.76
B58: 16º passo: Dívida da obra a ser paga (outra obra da carteira) | F58: =E129 -> 0
B63: Saldo de contrato | G63: Adiantamento de materiais não estocados
B74: Total | E74: =SUM(E64:E73) -> 0 | G74: Total | J74: =SUM(J64:J73) -> 0
B77: Adiantamento de serviços não medidos | G77: Estoque de materiais
G78: Material de canteiro (tapumes e contêineres) | J78: 17957.98
G79: Cimento e agregados | J79: 32137.4
G80: Aço CA-50 para fundação | J80: 19286.51
B88: Total | E88: =SUM(E78:E87) -> 0 | G88: Total | J88: =SUM(J78:J87) -> 69381.89
B91: Equipamentos comprados | G91: Receitas de personalizações
B92: Betoneira 400 L | E92: 9800
B93: Guincho de coluna | E93: 38500
B94: Container escritório (2 un.) | E94: 28000
B102: Total | E102: =SUM(E92:E101) -> 76300 | G102: Total | J102: =SUM(J92:J101) -> 0
B105: Contas a pagar dos medidos | G105: Itens apontados irregularmente no relatório
B106: Medição de terraplenagem · NF 28131 | E106: 15519.77
B107: Locação de equipamentos · NF 81518 | E107: 15339.69
B108: Encargos e INSS do mês · NF 1830 | E108: 15593.2
B115: Total | E115: =SUM(E106:E114) -> 46452.66 | G115: Total | J115: =SUM(J106:J114) -> 0
B118: Dívida da obra a ser paga
B129: Total | E129: =SUM(E119:E128) -> 0
B132: RESULTADO PARA UTILIZAR NA APRESENTAÇÃO
G135: Tabela informativa do desembolso do mês
C136: Projeto | D136: =D24 -> TIROL | G136: Valor previsto para o mês | J136: 267825.79
C137: Orçamento | D137: =J28 -> 30491200 | G137: Valor desembolsado no mês | J137: 257866.07
C138: Tipo do orçamento | D138: =J29 -> Orçamento legal | G138: Diferença entre o previsto e o desembolsado | J138: =J137-J136 -> -9959.72
C139: Mês | D139: =E26 -> 46143 | G139: Justificativa para diferença acima de 10% (obrigatória)
C140: % previsto do mês | D140: =F31 -> 0.0163
C141: % executado do mês | D141: =F33 -> 0.0082
C142: % previsto acumulado | D142: =F35 -> 0.0383
C143: % executado acumulado | D143: =F37 -> 0.0196
B145: 01 | C145: Crédito do orçamento | D145: =F39 -> 597627.52 | E145: =D145/$D$137 -> 0.0196
B146: 02 | C146: Saldo de contrato | D146: =F41 -> 0 | E146: =D146/$D$137 -> 0
B147: 03 | C147: Adiantamento de serviços não medidos | D147: =F43 -> 0 | E147: =D147/$D$137 -> 0
B148: 04 | C148: Adiantamento de materiais não estocados | D148: =F45 -> 0 | E148: =D148/$D$137 -> 0
B149: 05 | C149: Estoque de materiais | D149: =F47 -> 69381.89 | E149: =D149/$D$137 -> 0.0022754726
B150: 06 | C150: Equipamentos (valor de mercado) | D150: =F49 -> 76300 | E150: =D150/$D$137 -> 0.0025023613
B151: 07 | C151: Receita de personalizações | D151: =F51 -> 0 | E151: =D151/$D$137 -> 0
B152: 08 | C152: Contas a pagar dos medidos | D152: =F53 -> 46452.66 | E152: =D152/$D$137 -> 0.0015234776
B153: 09 | C153: Valor desembolsado (corrigido) | D153: =F56 -> 618175.76 | E153: =D153/$D$137 -> 0.020273907
B154: 10 | C154: Dívida da obra a ser paga | D154: =F58 -> 0 | E154: =D154/$D$137 -> 0
C155: Resultado mensal da obra | D155: =D145+D146+D147+D148+D149+D150+D151-D152-D153-D154 -> 78680.99 | E155: =D155/D137 -> 0.0025804491
C156: Resultado do mês anterior | D156: =ABR26!D155 -> 78364.73 | E156: =ABR26!E155 -> 0.002580563
B160: Significado de cada item
B162: Crédito do orçamento:
B163: Quanto a obra podia ter gasto pelo que executou: orçamento × executado acumulado.
B164: Saldo de contrato:
B165: Desconto obtido num contrato e ainda não realizado; abatido à medida que o serviço é medido.
B166: Adiantamento de serviços não medidos:
B167: Sinal pago de contrato ainda não medido (ex.: elevadores).
B168: Adiantamento de materiais não estocados:
B169: Material pago que ainda não chegou à obra (ex.: esquadrias).
B170: Estoque de materiais:
B171: Material no almoxarifado, ainda não aplicado, informado pelo almoxarife.
B172: Equipamentos (valor de mercado):
... B181: Material de outra obra da carteira usado nesta: custo da obra, desconta do resultado (versão 01 da planilha).

Sheet JUN26
B2: ANÁLISE DE DESEMPENHO ECONÔMICO DA OBRA
B3: Construtora fictícia de Natal/RN · portfólio Vizu Dados · dados inventados
B4: Versão 01 · revisão de 01/09/2025: a dívida da obra passa a descontar do resultado
B18: Célula editável
B19: Resultado (não editar)
B20: Tabela anexada
B21: % relacionada
B24: 1º passo: Projeto (definir o empreendimento) | D24: TIROL
B26: 2º passo: Mês de análise (definir o mês de referência) | E26: 46174
B28: 3º passo: Orçamento da obra projetado (com INCC no a realizar) | J28: 30615100
B29: Tipo do orçamento | J29: Orçamento legal
B31: 4º passo: Previsto do mês (incluir o % do cronograma) | F31: 0.0202
B33: 5º passo: Executado do mês (incluir o % medido) | F33: 0.0109
B35: 6º passo: Previsto acumulado do mês | F35: 0.0585
B37: 7º passo: Executado acumulado do mês | F37: 0.0305
B39: 8º passo: Crédito do orçamento (executado acumulado × orçamento) | F39: =F37*J28 -> 933760.55
B41: 8º passo (cont.): Saldo de contrato (tabela) | F41: =E74 -> 0
B43: 9º passo: Adiantamento de serviços não medidos (tabela) | F43: =E88 -> 0
B45: 10º passo: Adiantamento de materiais não estocados (tabela) | F45: =J74 -> 0
B47: 11º passo: Estoque de materiais (almoxarifado) | F47: =J88 -> 52207.08
B49: 12º passo: Equipamentos comprados (valor de mercado) | F49: =E102 -> 76300
B51: 13º passo: Receitas de personalizações (tabela) | F51: =J102 -> 0
B53: 14º passo: Contas a pagar dos medidos (relatório a pagar) | F53: =E115 -> 61769.32
B55: 15º passo: Valor desembolsado pela obra (relatório conferido) | F55: 919552.74
B56: Valor corrigido (sem os itens apontados irregularmente) | F56: =F55-J115 -> 919552.74
B58: 16º passo: Dívida da obra a ser paga (outra obra da carteira) | F58: =E129 -> 0
B63: Saldo de contrato | G63: Adiantamento de materiais não estocados
B74: Total | E74: =SUM(E64:E73) -> 0 | G74: Total | J74: =SUM(J64:J73) -> 0
B77: Adiantamento de serviços não medidos | G77: Estoque de materiais
G78: Material de canteiro (tapumes e contêineres) | J78: 15852.21
G79: Cimento e agregados | J79: 18350.43
G80: Aço CA-50 para fundação | J80: 18004.44
B88: Total | E88: =SUM(E78:E87) -> 0 | G88: Total | J88: =SUM(J78:J87) -> 52207.08
B91: Equipamentos comprados | G91: Receitas de personalizações
B92: Betoneira 400 L | E92: 9800
B93: Guincho de coluna | E93: 38500
B94: Container escritório (2 un.) | E94: 28000
B102: Total | E102: =SUM(E92:E101) -> 76300 | G102: Total | J102: =SUM(J92:J101) -> 0
B105: Contas a pagar dos medidos | G105: Itens apontados irregularmente no relatório
B106: Medição de terraplenagem · NF 41637 | E106: 17974.73
B107: Locação de equipamentos · NF 36713 | E107: 14206.69
B108: Encargos e INSS do mês · NF 25665 | E108: 29587.9
B115: Total | E115: =SUM(E106:E114) -> 61769.32 | G115: Total | J115: =SUM(J106:J114) -> 0
B118: Dívida da obra a ser paga
B129: Total | E129: =SUM(E119:E128) -> 0
B132: RESULTADO PARA UTILIZAR NA APRESENTAÇÃO
G135: Tabela informativa do desembolso do mês
C136: Projeto | D136: =D24 -> TIROL | G136: Valor previsto para o mês | J136: 305938.79
C137: Orçamento | D137: =J28 -> 30615100 | G137: Valor desembolsado no mês | J137: 301376.98
C138: Tipo do orçamento | D138: =J29 -> Orçamento legal | G138: Diferença entre o previsto e o desembolsado | J138: =J137-J136 -> -4561.81
C139: Mês | D139: =E26 -> 46174 | G139: Justificativa para diferença acima de 10% (obrigatória)
C140: % previsto do mês | D140: =F31 -> 0.0202
C141: % executado do mês | D141: =F33 -> 0.0109
C142: % previsto acumulado | D142: =F35 -> 0.0585
C143: % executado acumulado | D143: =F37 -> 0.0305
B145: 01 | C145: Crédito do orçamento | D145: =F39 -> 933760.55 | E145: =D145/$D$137 -> 0.0305
B146: 02 | C146: Saldo de contrato | D146: =F41 -> 0 | E146: =D146/$D$137 -> 0
B147: 03 | C147: Adiantamento de serviços não medidos | D147: =F43 -> 0 | E147: =D147/$D$137 -> 0
B148: 04 | C148: Adiantamento de materiais não estocados | D148: =F45 -> 0 | E148: =D148/$D$137 -> 0
B149: 05 | C149: Estoque de materiais | D149: =F47 -> 52207.08 | E149: =D149/$D$137 -> 0.0017052722
B150: 06 | C150: Equipamentos (valor de mercado) | D150: =F49 -> 76300 | E150: =D150/$D$137 -> 0.0024922342
B151: 07 | C151: Receita de personalizações | D151: =F51 -> 0 | E151: =D151/$D$137 -> 0
B152: 08 | C152: Contas a pagar dos medidos | D152: =F53 -> 61769.32 | E152: =D152/$D$137 -> 0.0020176096
B153: 09 | C153: Valor desembolsado (corrigido) | D153: =F56 -> 919552.74 | E153: =D153/$D$137 -> 0.030035921
B154: 10 | C154: Dívida da obra a ser paga | D154: =F58 -> 0 | E154: =D154/$D$137 -> 0
C155: Resultado mensal da obra | D155: =D145+D146+D147+D148+D149+D150+D151-D152-D153-D154 -> 80945.57 | E155: =D155/D137 -> 0.0026439754
C156: Resultado do mês anterior | D156: =MAI26!D155 -> 78680.99 | E156: =MAI26!E155 -> 0.0025804491
B160: Significado de cada item
B162: Crédito do orçamento:
B163: Quanto a obra podia ter gasto pelo que executou: orçamento × executado acumulado.
B164: Saldo de contrato:
B165: Desconto obtido num contrato e ainda não realizado; abatido à medida que o serviço é medido.
B166: Adiantamento de serviços não medidos:
B167: Sinal pago de contrato ainda não medido (ex.: elevadores).
B168: Adiantamento de materiais não estocados:
B169: Material pago que ainda não chegou à obra (ex.: esquadrias).
B170: Estoque de materiais:
B171: Material no almoxarifado, ainda não aplicado, informado pelo almoxarife.
B172: Equipamentos (valor de mercado):
... B181: Material de outra obra da carteira usado nesta: custo da obra, desconta do resultado (versão 01 da planilha).

Sheet JUL26
B2: ANÁLISE DE DESEMPENHO ECONÔMICO DA OBRA
B3: Construtora fictícia de Natal/RN · portfólio Vizu Dados · dados inventados
B4: Versão 01 · revisão de 01/09/2025: a dívida da obra passa a descontar do resultado
B18: Célula editável
B19: Resultado (não editar)
B20: Tabela anexada
B21: % relacionada
B24: 1º passo: Projeto (definir o empreendimento) | D24: TIROL
B26: 2º passo: Mês de análise (definir o mês de referência) | E26: 46204
B28: 3º passo: Orçamento da obra projetado (com INCC no a realizar) | J28: 30739000
B29: Tipo do orçamento | J29: Orçamento legal
B31: 4º passo: Previsto do mês (incluir o % do cronograma) | F31: 0.0239
B33: 5º passo: Executado do mês (incluir o % medido) | F33: 0.014
B35: 6º passo: Previsto acumulado do mês | F35: 0.0824
B37: 7º passo: Executado acumulado do mês | F37: 0.0445
B39: 8º passo: Crédito do orçamento (executado acumulado × orçamento) | F39: =F37*J28 -> 1367885.5
B41: 8º passo (cont.): Saldo de contrato (tabela) | F41: =E74 -> 0
B43: 9º passo: Adiantamento de serviços não medidos (tabela) | F43: =E88 -> 0
B45: 10º passo: Adiantamento de materiais não estocados (tabela) | F45: =J74 -> 0
B47: 11º passo: Estoque de materiais (almoxarifado) | F47: =J88 -> 72027.41
B49: 12º passo: Equipamentos comprados (valor de mercado) | F49: =E102 -> 76300
B51: 13º passo: Receitas de personalizações (tabela) | F51: =J102 -> 0
B53: 14º passo: Contas a pagar dos medidos (relatório a pagar) | F53: =E115 -> 76291.84
B55: 15º passo: Valor desembolsado pela obra (relatório conferido) | F55: 1355462.7
B56: Valor corrigido (sem os itens apontados irregularmente) | F56: =F55-J115 -> 1355462.7
B58: 16º passo: Dívida da obra a ser paga (outra obra da carteira) | F58: =E129 -> 0
B63: Saldo de contrato | G63: Adiantamento de materiais não estocados
B74: Total | E74: =SUM(E64:E73) -> 0 | G74: Total | J74: =SUM(J64:J73) -> 0
B77: Adiantamento de serviços não medidos | G77: Estoque de materiais
G78: Material de canteiro (tapumes e contêineres) | J78: 33436.14
G79: Cimento e agregados | J79: 22338.31
G80: Aço CA-50 para fundação | J80: 16252.96
B88: Total | E88: =SUM(E78:E87) -> 0 | G88: Total | J88: =SUM(J78:J87) -> 72027.41
B91: Equipamentos comprados | G91: Receitas de personalizações
B92: Betoneira 400 L | E92: 9800
B93: Guincho de coluna | E93: 38500
B94: Container escritório (2 un.) | E94: 28000
B102: Total | E102: =SUM(E92:E101) -> 76300 | G102: Total | J102: =SUM(J92:J101) -> 0
B105: Contas a pagar dos medidos | G105: Itens apontados irregularmente no relatório
B106: Medição de terraplenagem · NF 61117 | E106: 26103.05
B107: Locação de equipamentos · NF 61675 | E107: 19094.38
B108: Encargos e INSS do mês · NF 62899 | E108: 31094.41
B115: Total | E115: =SUM(E106:E114) -> 76291.84 | G115: Total | J115: =SUM(J106:J114) -> 0
B118: Dívida da obra a ser paga
B129: Total | E129: =SUM(E119:E128) -> 0
B132: RESULTADO PARA UTILIZAR NA APRESENTAÇÃO
G135: Tabela informativa do desembolso do mês
C136: Projeto | D136: =D24 -> TIROL | G136: Valor previsto para o mês | J136: 440271.03
C137: Orçamento | D137: =J28 -> 30739000 | G137: Valor desembolsado no mês | J137: 435909.97
C138: Tipo do orçamento | D138: =J29 -> Orçamento legal | G138: Diferença entre o previsto e o desembolsado | J138: =J137-J136 -> -4361.06
C139: Mês | D139: =E26 -> 46204 | G139: Justificativa para diferença acima de 10% (obrigatória)
C140: % previsto do mês | D140: =F31 -> 0.0239
C141: % executado do mês | D141: =F33 -> 0.014
C142: % previsto acumulado | D142: =F35 -> 0.0824
C143: % executado acumulado | D143: =F37 -> 0.0445
B145: 01 | C145: Crédito do orçamento | D145: =F39 -> 1367885.5 | E145: =D145/$D$137 -> 0.0445
B146: 02 | C146: Saldo de contrato | D146: =F41 -> 0 | E146: =D146/$D$137 -> 0
B147: 03 | C147: Adiantamento de serviços não medidos | D147: =F43 -> 0 | E147: =D147/$D$137 -> 0
B148: 04 | C148: Adiantamento de materiais não estocados | D148: =F45 -> 0 | E148: =D148/$D$137 -> 0
B149: 05 | C149: Estoque de materiais | D149: =F47 -> 72027.41 | E149: =D149/$D$137 -> 0.002343193
B150: 06 | C150: Equipamentos (valor de mercado) | D150: =F49 -> 76300 | E150: =D150/$D$137 -> 0.0024821888
B151: 07 | C151: Receita de personalizações | D151: =F51 -> 0 | E151: =D151/$D$137 -> 0
B152: 08 | C152: Contas a pagar dos medidos | D152: =F53 -> 76291.84 | E152: =D152/$D$137 -> 0.0024819233
B153: 09 | C153: Valor desembolsado (corrigido) | D153: =F56 -> 1355462.7 | E153: =D153/$D$137 -> 0.044095862
B154: 10 | C154: Dívida da obra a ser paga | D154: =F58 -> 0 | E154: =D154/$D$137 -> 0
C155: Resultado mensal da obra | D155: =D145+D146+D147+D148+D149+D150+D151-D152-D153-D154 -> 84458.36 | E155: =D155/D137 -> 0.0027475962
C156: Resultado do mês anterior | D156: =JUN26!D155 -> 80945.57 | E156: =JUN26!E155 -> 0.0026439754
B160: Significado de cada item
B162: Crédito do orçamento:
B163: Quanto a obra podia ter gasto pelo que executou: orçamento × executado acumulado.
B164: Saldo de contrato:
B165: Desconto obtido num contrato e ainda não realizado; abatido à medida que o serviço é medido.
B166: Adiantamento de serviços não medidos:
B167: Sinal pago de contrato ainda não medido (ex.: elevadores).
B168: Adiantamento de materiais não estocados:
B169: Material pago que ainda não chegou à obra (ex.: esquadrias).
B170: Estoque de materiais:
B171: Material no almoxarifado, ainda não aplicado, informado pelo almoxarife.
B172: Equipamentos (valor de mercado):
... B181: Material de outra obra da carteira usado nesta: custo da obra, desconta do resultado (versão 01 da planilha).

Sheet AGO26
B2: ANÁLISE DE DESEMPENHO ECONÔMICO DA OBRA
B3: Construtora fictícia de Natal/RN · portfólio Vizu Dados · dados inventados
B4: Versão 01 · revisão de 01/09/2025: a dívida da obra passa a descontar do resultado
B18: Célula editável
B19: Resultado (não editar)
B20: Tabela anexada
B21: % relacionada
B24: 1º passo: Projeto (definir o empreendimento) | D24: TIROL
B26: 2º passo: Mês de análise (definir o mês de referência) | E26: 46235
B28: 3º passo: Orçamento da obra projetado (com INCC no a realizar) | J28: 30862900
B29: Tipo do orçamento | J29: Orçamento legal
B31: 4º passo: Previsto do mês (incluir o % do cronograma) | F31: 0.0273
B33: 5º passo: Executado do mês (incluir o % medido) | F33: 0.0305
B35: 6º passo: Previsto acumulado do mês | F35: 0.1097
B37: 7º passo: Executado acumulado do mês | F37: 0.075
B39: 8º passo: Crédito do orçamento (executado acumulado × orçamento) | F39: =F37*J28 -> 2314717.5
B41: 8º passo (cont.): Saldo de contrato (tabela) | F41: =E74 -> 0
B43: 9º passo: Adiantamento de serviços não medidos (tabela) | F43: =E88 -> 0
B45: 10º passo: Adiantamento de materiais não estocados (tabela) | F45: =J74 -> 0
B47: 11º passo: Estoque de materiais (almoxarifado) | F47: =J88 -> 124014.79
B49: 12º passo: Equipamentos comprados (valor de mercado) | F49: =E102 -> 76300
B51: 13º passo: Receitas de personalizações (tabela) | F51: =J102 -> 0
B53: 14º passo: Contas a pagar dos medidos (relatório a pagar) | F53: =E115 -> 222069.64
B55: 15º passo: Valor desembolsado pela obra (relatório conferido) | F55: 2200572.3
B56: Valor corrigido (sem os itens apontados irregularmente) | F56: =F55-J115 -> 2200572.3
B58: 16º passo: Dívida da obra a ser paga (outra obra da carteira) | F58: =E129 -> 0
B63: Saldo de contrato | G63: Adiantamento de materiais não estocados
B74: Total | E74: =SUM(E64:E73) -> 0 | G74: Total | J74: =SUM(J64:J73) -> 0
B77: Adiantamento de serviços não medidos | G77: Estoque de materiais
G78: Aço CA-50 para blocos e baldrame | J78: 33997.89
G79: Cimento e agregados | J79: 45101.03
G80: Madeira para formas | J80: 44915.87
B88: Total | E88: =SUM(E78:E87) -> 0 | G88: Total | J88: =SUM(J78:J87) -> 124014.79
B91: Equipamentos comprados | G91: Receitas de personalizações
B92: Betoneira 400 L | E92: 9800
B93: Guincho de coluna | E93: 38500
B94: Container escritório (2 un.) | E94: 28000
B102: Total | E102: =SUM(E92:E101) -> 76300 | G102: Total | J102: =SUM(J92:J101) -> 0
B105: Contas a pagar dos medidos | G105: Itens apontados irregularmente no relatório
B106: Medição de fundação (estacas hélice) · NF 35049 | E106: 75849
B107: Concreto usinado dos blocos · NF 54356 | E107: 69600.44
B108: Encargos e INSS do mês · NF 37025 | E108: 76620.2
B115: Total | E115: =SUM(E106:E114) -> 222069.64 | G115: Total | J115: =SUM(J106:J114) -> 0
B118: Dívida da obra a ser paga
B129: Total | E129: =SUM(E119:E128) -> 0
B132: RESULTADO PARA UTILIZAR NA APRESENTAÇÃO
G135: Tabela informativa do desembolso do mês
C136: Projeto | D136: =D24 -> TIROL | G136: Valor previsto para o mês | J136: 813355.99
C137: Orçamento | D137: =J28 -> 30862900 | G137: Valor desembolsado no mês | J137: 845109.55
C138: Tipo do orçamento | D138: =J29 -> Orçamento legal | G138: Diferença entre o previsto e o desembolsado | J138: =J137-J136 -> 31753.56
C139: Mês | D139: =E26 -> 46235 | G139: Justificativa para diferença acima de 10% (obrigatória)
C140: % previsto do mês | D140: =F31 -> 0.0273
C141: % executado do mês | D141: =F33 -> 0.0305
C142: % previsto acumulado | D142: =F35 -> 0.1097
C143: % executado acumulado | D143: =F37 -> 0.075
B145: 01 | C145: Crédito do orçamento | D145: =F39 -> 2314717.5 | E145: =D145/$D$137 -> 0.075
B146: 02 | C146: Saldo de contrato | D146: =F41 -> 0 | E146: =D146/$D$137 -> 0
B147: 03 | C147: Adiantamento de serviços não medidos | D147: =F43 -> 0 | E147: =D147/$D$137 -> 0
B148: 04 | C148: Adiantamento de materiais não estocados | D148: =F45 -> 0 | E148: =D148/$D$137 -> 0
B149: 05 | C149: Estoque de materiais | D149: =F47 -> 124014.79 | E149: =D149/$D$137 -> 0.0040182481
B150: 06 | C150: Equipamentos (valor de mercado) | D150: =F49 -> 76300 | E150: =D150/$D$137 -> 0.0024722239
B151: 07 | C151: Receita de personalizações | D151: =F51 -> 0 | E151: =D151/$D$137 -> 0
B152: 08 | C152: Contas a pagar dos medidos | D152: =F53 -> 222069.64 | E152: =D152/$D$137 -> 0.0071953588
B153: 09 | C153: Valor desembolsado (corrigido) | D153: =F56 -> 2200572.3 | E153: =D153/$D$137 -> 0.071301539
B154: 10 | C154: Dívida da obra a ser paga | D154: =F58 -> 0 | E154: =D154/$D$137 -> 0
C155: Resultado mensal da obra | D155: =D145+D146+D147+D148+D149+D150+D151-D152-D153-D154 -> 92390.39 | E155: =D155/D137 -> 0.0029935745
C156: Resultado do mês anterior | D156: =JUL26!D155 -> 84458.36 | E156: =JUL26!E155 -> 0.0027475962
B160: Significado de cada item
B162: Crédito do orçamento:
B163: Quanto a obra podia ter gasto pelo que executou: orçamento × executado acumulado.
B164: Saldo de contrato:
B165: Desconto obtido num contrato e ainda não realizado; abatido à medida que o serviço é medido.
B166: Adiantamento de serviços não medidos:
B167: Sinal pago de contrato ainda não medido (ex.: elevadores).
B168: Adiantamento de materiais não estocados:
B169: Material pago que ainda não chegou à obra (ex.: esquadrias).
B170: Estoque de materiais:
B171: Material no almoxarifado, ainda não aplicado, informado pelo almoxarife.
B172: Equipamentos (valor de mercado):
... B181: Material de outra obra da carteira usado nesta: custo da obra, desconta do resultado (versão 01 da planilha).

Sheet SET26
B2: ANÁLISE DE DESEMPENHO ECONÔMICO DA OBRA
B3: Construtora fictícia de Natal/RN · portfólio Vizu Dados · dados inventados
B4: Versão 01 · revisão de 01/09/2025: a dívida da obra passa a descontar do resultado
B18: Célula editável
B19: Resultado (não editar)
B20: Tabela anexada
B21: % relacionada
B24: 1º passo: Projeto (definir o empreendimento) | D24: TIROL
B26: 2º passo: Mês de análise (definir o mês de referência) | E26: 46266
B28: 3º passo: Orçamento da obra projetado (com INCC no a realizar) | J28: 30986800
B29: Tipo do orçamento | J29: Orçamento legal
B31: 4º passo: Previsto do mês (incluir o % do cronograma) | F31: 0.0303
B33: 5º passo: Executado do mês (incluir o % medido) | F33: 0.0345
B35: 6º passo: Previsto acumulado do mês | F35: 0.14
B37: 7º passo: Executado acumulado do mês | F37: 0.1095
B39: 8º passo: Crédito do orçamento (executado acumulado × orçamento) | F39: =F37*J28 -> 3393054.6
B41: 8º passo (cont.): Saldo de contrato (tabela) | F41: =E74 -> 0
B43: 9º passo: Adiantamento de serviços não medidos (tabela) | F43: =E88 -> 0
B45: 10º passo: Adiantamento de materiais não estocados (tabela) | F45: =J74 -> 0
B47: 11º passo: Estoque de materiais (almoxarifado) | F47: =J88 -> 160077.95
B49: 12º passo: Equipamentos comprados (valor de mercado) | F49: =E102 -> 76300
B51: 13º passo: Receitas de personalizações (tabela) | F51: =J102 -> 0
B53: 14º passo: Contas a pagar dos medidos (relatório a pagar) | F53: =E115 -> 184188.73
B55: 15º passo: Valor desembolsado pela obra (relatório conferido) | F55: 3342014.8
B56: Valor corrigido (sem os itens apontados irregularmente) | F56: =F55-J115 -> 3342014.8
B58: 16º passo: Dívida da obra a ser paga (outra obra da carteira) | F58: =E129 -> 0
B63: Saldo de contrato | G63: Adiantamento de materiais não estocados
B74: Total | E74: =SUM(E64:E73) -> 0 | G74: Total | J74: =SUM(J64:J73) -> 0
B77: Adiantamento de serviços não medidos | G77: Estoque de materiais
G78: Aço CA-50 para blocos e baldrame | J78: 60155.18
G79: Cimento e agregados | J79: 50861.87
G80: Madeira para formas | J80: 49060.9
B88: Total | E88: =SUM(E78:E87) -> 0 | G88: Total | J88: =SUM(J78:J87) -> 160077.95
B91: Equipamentos comprados | G91: Receitas de personalizações
B92: Betoneira 400 L | E92: 9800
B93: Guincho de coluna | E93: 38500
B94: Container escritório (2 un.) | E94: 28000
B102: Total | E102: =SUM(E92:E101) -> 76300 | G102: Total | J102: =SUM(J92:J101) -> 0
B105: Contas a pagar dos medidos | G105: Itens apontados irregularmente no relatório
B106: Medição de fundação (estacas hélice) · NF 15819 | E106: 69346.47
B107: Concreto usinado dos blocos · NF 9713 | E107: 57595.99
B108: Encargos e INSS do mês · NF 4326 | E108: 57246.27
B115: Total | E115: =SUM(E106:E114) -> 184188.73 | G115: Total | J115: =SUM(J106:J114) -> 0
B118: Dívida da obra a ser paga
B129: Total | E129: =SUM(E119:E128) -> 0
B132: RESULTADO PARA UTILIZAR NA APRESENTAÇÃO
G135: Tabela informativa do desembolso do mês
C136: Projeto | D136: =D24 -> TIROL | G136: Valor previsto para o mês | J136: 1106074.8
C137: Orçamento | D137: =J28 -> 30986800 | G137: Valor desembolsado no mês | J137: 1141442.6
C138: Tipo do orçamento | D138: =J29 -> Orçamento legal | G138: Diferença entre o previsto e o desembolsado | J138: =J137-J136 -> 35367.81
C139: Mês | D139: =E26 -> 46266 | G139: Justificativa para diferença acima de 10% (obrigatória)
C140: % previsto do mês | D140: =F31 -> 0.0303
C141: % executado do mês | D141: =F33 -> 0.0345
C142: % previsto acumulado | D142: =F35 -> 0.14
C143: % executado acumulado | D143: =F37 -> 0.1095
B145: 01 | C145: Crédito do orçamento | D145: =F39 -> 3393054.6 | E145: =D145/$D$137 -> 0.1095
B146: 02 | C146: Saldo de contrato | D146: =F41 -> 0 | E146: =D146/$D$137 -> 0
B147: 03 | C147: Adiantamento de serviços não medidos | D147: =F43 -> 0 | E147: =D147/$D$137 -> 0
B148: 04 | C148: Adiantamento de materiais não estocados | D148: =F45 -> 0 | E148: =D148/$D$137 -> 0
B149: 05 | C149: Estoque de materiais | D149: =F47 -> 160077.95 | E149: =D149/$D$137 -> 0.0051660046
B150: 06 | C150: Equipamentos (valor de mercado) | D150: =F49 -> 76300 | E150: =D150/$D$137 -> 0.0024623388
B151: 07 | C151: Receita de personalizações | D151: =F51 -> 0 | E151: =D151/$D$137 -> 0
B152: 08 | C152: Contas a pagar dos medidos | D152: =F53 -> 184188.73 | E152: =D152/$D$137 -> 0.005944103
B153: 09 | C153: Valor desembolsado (corrigido) | D153: =F56 -> 3342014.8 | E153: =D153/$D$137 -> 0.10785285
B154: 10 | C154: Dívida da obra a ser paga | D154: =F58 -> 0 | E154: =D154/$D$137 -> 0
C155: Resultado mensal da obra | D155: =D145+D146+D147+D148+D149+D150+D151-D152-D153-D154 -> 103229 | E155: =D155/D137 -> 0.0033313863
C156: Resultado do mês anterior | D156: =AGO26!D155 -> 92390.39 | E156: =AGO26!E155 -> 0.0029935745
B160: Significado de cada item
B162: Crédito do orçamento:
B163: Quanto a obra podia ter gasto pelo que executou: orçamento × executado acumulado.
B164: Saldo de contrato:
B165: Desconto obtido num contrato e ainda não realizado; abatido à medida que o serviço é medido.
B166: Adiantamento de serviços não medidos:
B167: Sinal pago de contrato ainda não medido (ex.: elevadores).
B168: Adiantamento de materiais não estocados:
B169: Material pago que ainda não chegou à obra (ex.: esquadrias).
B170: Estoque de materiais:
B171: Material no almoxarifado, ainda não aplicado, informado pelo almoxarife.
B172: Equipamentos (valor de mercado):
... B181: Material de outra obra da carteira usado nesta: custo da obra, desconta do resultado (versão 01 da planilha).
