Workbook

Sheet LEIA-ME
B2: Análise Crítica · CAJUEIRO
B3: Dados fictícios: construtora inventada de Natal/RN, portfólio Vizu Dados.
B4: Uma aba por mês (MMMAA). Os campos são lidos pelo rótulo da coluna B.
B5: Versão 01 da planilha: a dívida da obra (item 10) desconta do resultado.

Sheet SET25
B2: ANÁLISE DE DESEMPENHO ECONÔMICO DA OBRA
B3: Construtora fictícia de Natal/RN · portfólio Vizu Dados · dados inventados
B4: Versão 01 · revisão de 01/09/2025: a dívida da obra passa a descontar do resultado
B18: Célula editável
B19: Resultado (não editar)
B20: Tabela anexada
B21: % relacionada
B24: 1º passo: Projeto (definir o empreendimento) | D24: CAJUEIRO
B26: 2º passo: Mês de análise (definir o mês de referência) | E26: 45901
B28: 3º passo: Orçamento da obra projetado (com INCC no a realizar) | J28: 21400000
B29: Tipo do orçamento | J29: Orçamento final
B31: 4º passo: Previsto do mês (incluir o % do cronograma) | F31: 0.0368
B33: 5º passo: Executado do mês (incluir o % medido) | F33: 0.0368
B35: 6º passo: Previsto acumulado do mês | F35: 0.67
B37: 7º passo: Executado acumulado do mês | F37: 0.655
B39: 8º passo: Crédito do orçamento (executado acumulado × orçamento) | F39: =F37*J28 -> 14017000
B41: 8º passo (cont.): Saldo de contrato (tabela) | F41: =E74 -> 0
B43: 9º passo: Adiantamento de serviços não medidos (tabela) | F43: =E88 -> 0
B45: 10º passo: Adiantamento de materiais não estocados (tabela) | F45: =J74 -> 0
B47: 11º passo: Estoque de materiais (almoxarifado) | F47: =J88 -> 236925.2
B49: 12º passo: Equipamentos comprados (valor de mercado) | F49: =E102 -> 183300
B51: 13º passo: Receitas de personalizações (tabela) | F51: =J102 -> 382000
B53: 14º passo: Contas a pagar dos medidos (relatório a pagar) | F53: =E115 -> 154979.44
B55: 15º passo: Valor desembolsado pela obra (relatório conferido) | F55: 14314736
B56: Valor corrigido (sem os itens apontados irregularmente) | F56: =F55-J115 -> 14314736
B58: 16º passo: Dívida da obra a ser paga (outra obra da carteira) | F58: =E129 -> 0
B63: Saldo de contrato | G63: Adiantamento de materiais não estocados
B74: Total | E74: =SUM(E64:E73) -> 0 | G74: Total | J74: =SUM(J64:J73) -> 0
B77: Adiantamento de serviços não medidos | G77: Estoque de materiais
G78: Blocos cerâmicos | J78: 61781.96
G79: Argamassa industrializada | J79: 44220.37
G80: Material hidrossanitário | J80: 31720.14
G81: Material elétrico (fios e cabos) | J81: 41041.31
G82: Revestimento cerâmico (compra antecipada) | J82: 58161.42
B88: Total | E88: =SUM(E78:E87) -> 0 | G88: Total | J88: =SUM(J78:J87) -> 236925.2
B91: Equipamentos comprados | G91: Receitas de personalizações
B92: Betoneira 400 L | E92: 9800 | G92: Unid. 501 · troca de piso da sala (cliente I. Moura) | J92: 200553.59
B93: Guincho de coluna | E93: 38500 | G93: Unid. 1603 · bancada da cozinha em quartzo (cliente J. Viana) | J93: 181446.41
B94: Andaime fachadeiro (lote) | E94: 64000
B95: Plataforma elevatória | E95: 71000
B102: Total | E102: =SUM(E92:E101) -> 183300 | G102: Total | J102: =SUM(J92:J101) -> 382000
B105: Contas a pagar dos medidos | G105: Itens apontados irregularmente no relatório
B106: Medição da empreiteira de alvenaria · NF 22849 | E106: 36484.25
B107: Medição de instalações hidráulicas · NF 33277 | E107: 42951.28
B108: Medição de instalações elétricas · NF 78149 | E108: 37865.25
B109: Encargos e INSS do mês · NF 11244 | E109: 37678.66
B115: Total | E115: =SUM(E106:E114) -> 154979.44 | G115: Total | J115: =SUM(J106:J114) -> 0
B118: Dívida da obra a ser paga
B129: Total | E129: =SUM(E119:E128) -> 0
B132: RESULTADO PARA UTILIZAR NA APRESENTAÇÃO
G135: Tabela informativa do desembolso do mês
C136: Projeto | D136: =D24 -> CAJUEIRO | G136: Valor previsto para o mês | J136: 1209946.3
C137: Orçamento | D137: =J28 -> 21400000 | G137: Valor desembolsado no mês | J137: 1242014.7
C138: Tipo do orçamento | D138: =J29 -> Orçamento final | G138: Diferença entre o previsto e o desembolsado | J138: =J137-J136 -> 32068.38
C139: Mês | D139: =E26 -> 45901 | G139: Justificativa para diferença acima de 10% (obrigatória)
C140: % previsto do mês | D140: =F31 -> 0.0368
C141: % executado do mês | D141: =F33 -> 0.0368
C142: % previsto acumulado | D142: =F35 -> 0.67
C143: % executado acumulado | D143: =F37 -> 0.655
B145: 01 | C145: Crédito do orçamento | D145: =F39 -> 14017000 | E145: =D145/$D$137 -> 0.655
B146: 02 | C146: Saldo de contrato | D146: =F41 -> 0 | E146: =D146/$D$137 -> 0
B147: 03 | C147: Adiantamento de serviços não medidos | D147: =F43 -> 0 | E147: =D147/$D$137 -> 0
B148: 04 | C148: Adiantamento de materiais não estocados | D148: =F45 -> 0 | E148: =D148/$D$137 -> 0
B149: 05 | C149: Estoque de materiais | D149: =F47 -> 236925.2 | E149: =D149/$D$137 -> 0.011071271
B150: 06 | C150: Equipamentos (valor de mercado) | D150: =F49 -> 183300 | E150: =D150/$D$137 -> 0.0085654206
B151: 07 | C151: Receita de personalizações | D151: =F51 -> 382000 | E151: =D151/$D$137 -> 0.017850467
B152: 08 | C152: Contas a pagar dos medidos | D152: =F53 -> 154979.44 | E152: =D152/$D$137 -> 0.0072420299
B153: 09 | C153: Valor desembolsado (corrigido) | D153: =F56 -> 14314736 | E153: =D153/$D$137 -> 0.66891291
B154: 10 | C154: Dívida da obra a ser paga | D154: =F58 -> 0 | E154: =D154/$D$137 -> 0
C155: Resultado mensal da obra | D155: =D145+D146+D147+D148+D149+D150+D151-D152-D153-D154 -> 349509.49 | E155: =D155/D137 -> 0.016332219
C156: Resultado do mês anterior
B160: Significado de cada item
B162: Crédito do orçamento:
B163: Quanto a obra podia ter gasto pelo que executou: orçamento × executado acumulado.
B164: Saldo de contrato:
B165: Desconto obtido num contrato e ainda não realizado; abatido à medida que o serviço é medido.
B166: Adiantamento de serviços não medidos:
B167: Sinal pago de contrato ainda não medido (ex.: elevadores).
B168: Adiantamento de materiais não estocados:
B169: Material pago que ainda não chegou à obra (ex.: esquadrias).
B170: Estoque de materiais:
B171: Material no almoxarifado, ainda não aplicado, informado pelo almoxarife.
B172: Equipamentos (valor de mercado):
... B181: Material de outra obra da carteira usado nesta: custo da obra, desconta do resultado (versão 01 da planilha).

Sheet OUT25
B2: ANÁLISE DE DESEMPENHO ECONÔMICO DA OBRA
B3: Construtora fictícia de Natal/RN · portfólio Vizu Dados · dados inventados
B4: Versão 01 · revisão de 01/09/2025: a dívida da obra passa a descontar do resultado
B18: Célula editável
B19: Resultado (não editar)
B20: Tabela anexada
B21: % relacionada
B24: 1º passo: Projeto (definir o empreendimento) | D24: CAJUEIRO
B26: 2º passo: Mês de análise (definir o mês de referência) | E26: 45931
B28: 3º passo: Orçamento da obra projetado (com INCC no a realizar) | J28: 21489880
B29: Tipo do orçamento | J29: Orçamento final
B31: 4º passo: Previsto do mês (incluir o % do cronograma) | F31: 0.0359
B33: 5º passo: Executado do mês (incluir o % medido) | F33: 0.0359
B35: 6º passo: Previsto acumulado do mês | F35: 0.7059
B37: 7º passo: Executado acumulado do mês | F37: 0.6909
B39: 8º passo: Crédito do orçamento (executado acumulado × orçamento) | F39: =F37*J28 -> 14847358
B41: 8º passo (cont.): Saldo de contrato (tabela) | F41: =E74 -> 0
B43: 9º passo: Adiantamento de serviços não medidos (tabela) | F43: =E88 -> 0
B45: 10º passo: Adiantamento de materiais não estocados (tabela) | F45: =J74 -> 0
B47: 11º passo: Estoque de materiais (almoxarifado) | F47: =J88 -> 240572.92
B49: 12º passo: Equipamentos comprados (valor de mercado) | F49: =E102 -> 183300
B51: 13º passo: Receitas de personalizações (tabela) | F51: =J102 -> 399500
B53: 14º passo: Contas a pagar dos medidos (relatório a pagar) | F53: =E115 -> 149338.74
B55: 15º passo: Valor desembolsado pela obra (relatório conferido) | F55: 15149965
B56: Valor corrigido (sem os itens apontados irregularmente) | F56: =F55-J115 -> 15149965
B58: 16º passo: Dívida da obra a ser paga (outra obra da carteira) | F58: =E129 -> 0
B63: Saldo de contrato | G63: Adiantamento de materiais não estocados
B74: Total | E74: =SUM(E64:E73) -> 0 | G74: Total | J74: =SUM(J64:J73) -> 0
B77: Adiantamento de serviços não medidos | G77: Estoque de materiais
G78: Blocos cerâmicos | J78: 40523.37
G79: Argamassa industrializada | J79: 44741.74
G80: Material hidrossanitário | J80: 55905.26
G81: Material elétrico (fios e cabos) | J81: 50588.27
G82: Revestimento cerâmico (compra antecipada) | J82: 48814.28
B88: Total | E88: =SUM(E78:E87) -> 0 | G88: Total | J88: =SUM(J78:J87) -> 240572.92
B91: Equipamentos comprados | G91: Receitas de personalizações
B92: Betoneira 400 L | E92: 9800 | G92: Unid. 501 · troca de piso da sala (cliente I. Moura) | J92: 209741.25
B93: Guincho de coluna | E93: 38500 | G93: Unid. 1603 · bancada da cozinha em quartzo (cliente J. Viana) | J93: 189758.75
B94: Andaime fachadeiro (lote) | E94: 64000
B95: Plataforma elevatória | E95: 71000
B102: Total | E102: =SUM(E92:E101) -> 183300 | G102: Total | J102: =SUM(J92:J101) -> 399500
B105: Contas a pagar dos medidos | G105: Itens apontados irregularmente no relatório
B106: Medição da empreiteira de alvenaria · NF 16641 | E106: 40748.34
B107: Medição de instalações hidráulicas · NF 77518 | E107: 29135.64
B108: Medição de instalações elétricas · NF 62299 | E108: 49117.14
B109: Encargos e INSS do mês · NF 28795 | E109: 30337.62
B115: Total | E115: =SUM(E106:E114) -> 149338.74 | G115: Total | J115: =SUM(J106:J114) -> 0
B118: Dívida da obra a ser paga
B129: Total | E129: =SUM(E119:E128) -> 0
B132: RESULTADO PARA UTILIZAR NA APRESENTAÇÃO
G135: Tabela informativa do desembolso do mês
C136: Projeto | D136: =D24 -> CAJUEIRO | G136: Valor previsto para o mês | J136: 814855.02
C137: Orçamento | D137: =J28 -> 21489880 | G137: Valor desembolsado no mês | J137: 835229.2
C138: Tipo do orçamento | D138: =J29 -> Orçamento final | G138: Diferença entre o previsto e o desembolsado | J138: =J137-J136 -> 20374.18
C139: Mês | D139: =E26 -> 45931 | G139: Justificativa para diferença acima de 10% (obrigatória)
C140: % previsto do mês | D140: =F31 -> 0.0359
C141: % executado do mês | D141: =F33 -> 0.0359
C142: % previsto acumulado | D142: =F35 -> 0.7059
C143: % executado acumulado | D143: =F37 -> 0.6909
B145: 01 | C145: Crédito do orçamento | D145: =F39 -> 14847358 | E145: =D145/$D$137 -> 0.6909
B146: 02 | C146: Saldo de contrato | D146: =F41 -> 0 | E146: =D146/$D$137 -> 0
B147: 03 | C147: Adiantamento de serviços não medidos | D147: =F43 -> 0 | E147: =D147/$D$137 -> 0
B148: 04 | C148: Adiantamento de materiais não estocados | D148: =F45 -> 0 | E148: =D148/$D$137 -> 0
B149: 05 | C149: Estoque de materiais | D149: =F47 -> 240572.92 | E149: =D149/$D$137 -> 0.011194707
B150: 06 | C150: Equipamentos (valor de mercado) | D150: =F49 -> 183300 | E150: =D150/$D$137 -> 0.0085295963
B151: 07 | C151: Receita de personalizações | D151: =F51 -> 399500 | E151: =D151/$D$137 -> 0.018590146
B152: 08 | C152: Contas a pagar dos medidos | D152: =F53 -> 149338.74 | E152: =D152/$D$137 -> 0.0069492589
B153: 09 | C153: Valor desembolsado (corrigido) | D153: =F56 -> 15149965 | E153: =D153/$D$137 -> 0.70498139
B154: 10 | C154: Dívida da obra a ser paga | D154: =F58 -> 0 | E154: =D154/$D$137 -> 0
C155: Resultado mensal da obra | D155: =D145+D146+D147+D148+D149+D150+D151-D152-D153-D154 -> 371426.8 | E155: =D155/D137 -> 0.017283801
C156: Resultado do mês anterior | D156: =SET25!D155 -> 349509.49 | E156: =SET25!E155 -> 0.016332219
B160: Significado de cada item
B162: Crédito do orçamento:
B163: Quanto a obra podia ter gasto pelo que executou: orçamento × executado acumulado.
B164: Saldo de contrato:
B165: Desconto obtido num contrato e ainda não realizado; abatido à medida que o serviço é medido.
B166: Adiantamento de serviços não medidos:
B167: Sinal pago de contrato ainda não medido (ex.: elevadores).
B168: Adiantamento de materiais não estocados:
B169: Material pago que ainda não chegou à obra (ex.: esquadrias).
B170: Estoque de materiais:
B171: Material no almoxarifado, ainda não aplicado, informado pelo almoxarife.
B172: Equipamentos (valor de mercado):
... B181: Material de outra obra da carteira usado nesta: custo da obra, desconta do resultado (versão 01 da planilha).

Sheet NOV25
B2: ANÁLISE DE DESEMPENHO ECONÔMICO DA OBRA
B3: Construtora fictícia de Natal/RN · portfólio Vizu Dados · dados inventados
B4: Versão 01 · revisão de 01/09/2025: a dívida da obra passa a descontar do resultado
B18: Célula editável
B19: Resultado (não editar)
B20: Tabela anexada
B21: % relacionada
B24: 1º passo: Projeto (definir o empreendimento) | D24: CAJUEIRO
B26: 2º passo: Mês de análise (definir o mês de referência) | E26: 45962
B28: 3º passo: Orçamento da obra projetado (com INCC no a realizar) | J28: 21579760
B29: Tipo do orçamento | J29: Orçamento final
B31: 4º passo: Previsto do mês (incluir o % do cronograma) | F31: 0.0348
B33: 5º passo: Executado do mês (incluir o % medido) | F33: 0.0348
B35: 6º passo: Previsto acumulado do mês | F35: 0.7407
B37: 7º passo: Executado acumulado do mês | F37: 0.7257
B39: 8º passo: Crédito do orçamento (executado acumulado × orçamento) | F39: =F37*J28 -> 15660432
B41: 8º passo (cont.): Saldo de contrato (tabela) | F41: =E74 -> 0
B43: 9º passo: Adiantamento de serviços não medidos (tabela) | F43: =E88 -> 0
B45: 10º passo: Adiantamento de materiais não estocados (tabela) | F45: =J74 -> 0
B47: 11º passo: Estoque de materiais (almoxarifado) | F47: =J88 -> 284802.3
B49: 12º passo: Equipamentos comprados (valor de mercado) | F49: =E102 -> 183300
B51: 13º passo: Receitas de personalizações (tabela) | F51: =J102 -> 417000
B53: 14º passo: Contas a pagar dos medidos (relatório a pagar) | F53: =E115 -> 125336.38
B55: 15º passo: Valor desembolsado pela obra (relatório conferido) | F55: 16025757
B56: Valor corrigido (sem os itens apontados irregularmente) | F56: =F55-J115 -> 16025757
B58: 16º passo: Dívida da obra a ser paga (outra obra da carteira) | F58: =E129 -> 0
B63: Saldo de contrato | G63: Adiantamento de materiais não estocados
B74: Total | E74: =SUM(E64:E73) -> 0 | G74: Total | J74: =SUM(J64:J73) -> 0
B77: Adiantamento de serviços não medidos | G77: Estoque de materiais
G78: Blocos cerâmicos | J78: 40643.05
G79: Argamassa industrializada | J79: 74953.6
G80: Material hidrossanitário | J80: 61944.46
G81: Material elétrico (fios e cabos) | J81: 52782.66
G82: Revestimento cerâmico (compra antecipada) | J82: 54478.53
B88: Total | E88: =SUM(E78:E87) -> 0 | G88: Total | J88: =SUM(J78:J87) -> 284802.3
B91: Equipamentos comprados | G91: Receitas de personalizações
B92: Betoneira 400 L | E92: 9800 | G92: Unid. 501 · troca de piso da sala (cliente I. Moura) | J92: 142707.75
B93: Guincho de coluna | E93: 38500 | G93: Unid. 1603 · bancada da cozinha em quartzo (cliente J. Viana) | J93: 129111.67
B94: Andaime fachadeiro (lote) | E94: 64000 | G94: Unid. 401 · planta com home office (cliente K. Saraiva) | J94: 145180.58
B95: Plataforma elevatória | E95: 71000
B102: Total | E102: =SUM(E92:E101) -> 183300 | G102: Total | J102: =SUM(J92:J101) -> 417000
B105: Contas a pagar dos medidos | G105: Itens apontados irregularmente no relatório
B106: Medição da empreiteira de alvenaria · NF 84920 | E106: 41085.66
B107: Medição de instalações hidráulicas · NF 20305 | E107: 33148.07
B108: Medição de instalações elétricas · NF 44627 | E108: 26280
B109: Encargos e INSS do mês · NF 78679 | E109: 24822.65
B115: Total | E115: =SUM(E106:E114) -> 125336.38 | G115: Total | J115: =SUM(J106:J114) -> 0
B118: Dívida da obra a ser paga
B129: Total | E129: =SUM(E119:E128) -> 0
B132: RESULTADO PARA UTILIZAR NA APRESENTAÇÃO
G135: Tabela informativa do desembolso do mês
C136: Projeto | D136: =D24 -> CAJUEIRO | G136: Valor previsto para o mês | J136: 884871.41
C137: Orçamento | D137: =J28 -> 21579760 | G137: Valor desembolsado no mês | J137: 875791.96
C138: Tipo do orçamento | D138: =J29 -> Orçamento final | G138: Diferença entre o previsto e o desembolsado | J138: =J137-J136 -> -9079.45
C139: Mês | D139: =E26 -> 45962 | G139: Justificativa para diferença acima de 10% (obrigatória)
C140: % previsto do mês | D140: =F31 -> 0.0348
C141: % executado do mês | D141: =F33 -> 0.0348
C142: % previsto acumulado | D142: =F35 -> 0.7407
C143: % executado acumulado | D143: =F37 -> 0.7257
B145: 01 | C145: Crédito do orçamento | D145: =F39 -> 15660432 | E145: =D145/$D$137 -> 0.7257
B146: 02 | C146: Saldo de contrato | D146: =F41 -> 0 | E146: =D146/$D$137 -> 0
B147: 03 | C147: Adiantamento de serviços não medidos | D147: =F43 -> 0 | E147: =D147/$D$137 -> 0
B148: 04 | C148: Adiantamento de materiais não estocados | D148: =F45 -> 0 | E148: =D148/$D$137 -> 0
B149: 05 | C149: Estoque de materiais | D149: =F47 -> 284802.3 | E149: =D149/$D$137 -> 0.013197658
B150: 06 | C150: Equipamentos (valor de mercado) | D150: =F49 -> 183300 | E150: =D150/$D$137 -> 0.0084940704
B151: 07 | C151: Receita de personalizações | D151: =F51 -> 417000 | E151: =D151/$D$137 -> 0.019323663
B152: 08 | C152: Contas a pagar dos medidos | D152: =F53 -> 125336.38 | E152: =D152/$D$137 -> 0.0058080525
B153: 09 | C153: Valor desembolsado (corrigido) | D153: =F56 -> 16025757 | E153: =D153/$D$137 -> 0.74262909
B154: 10 | C154: Dívida da obra a ser paga | D154: =F58 -> 0 | E154: =D154/$D$137 -> 0
C155: Resultado mensal da obra | D155: =D145+D146+D147+D148+D149+D150+D151-D152-D153-D154 -> 394440.32 | E155: =D155/D137 -> 0.018278253
C156: Resultado do mês anterior | D156: =OUT25!D155 -> 371426.8 | E156: =OUT25!E155 -> 0.017283801
B160: Significado de cada item
B162: Crédito do orçamento:
B163: Quanto a obra podia ter gasto pelo que executou: orçamento × executado acumulado.
B164: Saldo de contrato:
B165: Desconto obtido num contrato e ainda não realizado; abatido à medida que o serviço é medido.
B166: Adiantamento de serviços não medidos:
B167: Sinal pago de contrato ainda não medido (ex.: elevadores).
B168: Adiantamento de materiais não estocados:
B169: Material pago que ainda não chegou à obra (ex.: esquadrias).
B170: Estoque de materiais:
B171: Material no almoxarifado, ainda não aplicado, informado pelo almoxarife.
B172: Equipamentos (valor de mercado):
... B181: Material de outra obra da carteira usado nesta: custo da obra, desconta do resultado (versão 01 da planilha).

Sheet DEZ25
B2: ANÁLISE DE DESEMPENHO ECONÔMICO DA OBRA
B3: Construtora fictícia de Natal/RN · portfólio Vizu Dados · dados inventados
B4: Versão 01 · revisão de 01/09/2025: a dívida da obra passa a descontar do resultado
B18: Célula editável
B19: Resultado (não editar)
B20: Tabela anexada
B21: % relacionada
B24: 1º passo: Projeto (definir o empreendimento) | D24: CAJUEIRO
B26: 2º passo: Mês de análise (definir o mês de referência) | E26: 45992
B28: 3º passo: Orçamento da obra projetado (com INCC no a realizar) | J28: 21669640
B29: Tipo do orçamento | J29: Orçamento final
B31: 4º passo: Previsto do mês (incluir o % do cronograma) | F31: 0.0335
B33: 5º passo: Executado do mês (incluir o % medido) | F33: 0.0332
B35: 6º passo: Previsto acumulado do mês | F35: 0.7742
B37: 7º passo: Executado acumulado do mês | F37: 0.7589
B39: 8º passo: Crédito do orçamento (executado acumulado × orçamento) | F39: =F37*J28 -> 16445090
B41: 8º passo (cont.): Saldo de contrato (tabela) | F41: =E74 -> 0
B43: 9º passo: Adiantamento de serviços não medidos (tabela) | F43: =E88 -> 0
B45: 10º passo: Adiantamento de materiais não estocados (tabela) | F45: =J74 -> 0
B47: 11º passo: Estoque de materiais (almoxarifado) | F47: =J88 -> 260170.11
B49: 12º passo: Equipamentos comprados (valor de mercado) | F49: =E102 -> 183300
B51: 13º passo: Receitas de personalizações (tabela) | F51: =J102 -> 434500
B53: 14º passo: Contas a pagar dos medidos (relatório a pagar) | F53: =E115 -> 151887.8
B55: 15º passo: Valor desembolsado pela obra (relatório conferido) | F55: 16752826
B56: Valor corrigido (sem os itens apontados irregularmente) | F56: =F55-J115 -> 16752826
B58: 16º passo: Dívida da obra a ser paga (outra obra da carteira) | F58: =E129 -> 0
B63: Saldo de contrato | G63: Adiantamento de materiais não estocados
B74: Total | E74: =SUM(E64:E73) -> 0 | G74: Total | J74: =SUM(J64:J73) -> 0
B77: Adiantamento de serviços não medidos | G77: Estoque de materiais
G78: Blocos cerâmicos | J78: 39373.26
G79: Argamassa industrializada | J79: 48983.29
G80: Material hidrossanitário | J80: 65189.66
G81: Material elétrico (fios e cabos) | J81: 62713.38
G82: Revestimento cerâmico (compra antecipada) | J82: 43910.52
B88: Total | E88: =SUM(E78:E87) -> 0 | G88: Total | J88: =SUM(J78:J87) -> 260170.11
B91: Equipamentos comprados | G91: Receitas de personalizações
B92: Betoneira 400 L | E92: 9800 | G92: Unid. 501 · troca de piso da sala (cliente I. Moura) | J92: 148696.69
B93: Guincho de coluna | E93: 38500 | G93: Unid. 1603 · bancada da cozinha em quartzo (cliente J. Viana) | J93: 134530.03
B94: Andaime fachadeiro (lote) | E94: 64000 | G94: Unid. 401 · planta com home office (cliente K. Saraiva) | J94: 151273.28
B95: Plataforma elevatória | E95: 71000
B102: Total | E102: =SUM(E92:E101) -> 183300 | G102: Total | J102: =SUM(J92:J101) -> 434500
B105: Contas a pagar dos medidos | G105: Itens apontados irregularmente no relatório
B106: Medição da empreiteira de alvenaria · NF 30792 | E106: 42844.51
B107: Medição de instalações hidráulicas · NF 91040 | E107: 51871.64
B108: Medição de instalações elétricas · NF 24305 | E108: 27272.57
B109: Encargos e INSS do mês · NF 32061 | E109: 29899.08
B115: Total | E115: =SUM(E106:E114) -> 151887.8 | G115: Total | J115: =SUM(J106:J114) -> 0
B118: Dívida da obra a ser paga
B129: Total | E129: =SUM(E119:E128) -> 0
B132: RESULTADO PARA UTILIZAR NA APRESENTAÇÃO
G135: Tabela informativa do desembolso do mês
C136: Projeto | D136: =D24 -> CAJUEIRO | G136: Valor previsto para o mês | J136: 749141.63
C137: Orçamento | D137: =J28 -> 21669640 | G137: Valor desembolsado no mês | J137: 727069.04
C138: Tipo do orçamento | D138: =J29 -> Orçamento final | G138: Diferença entre o previsto e o desembolsado | J138: =J137-J136 -> -22072.59
C139: Mês | D139: =E26 -> 45992 | G139: Justificativa para diferença acima de 10% (obrigatória)
C140: % previsto do mês | D140: =F31 -> 0.0335
C141: % executado do mês | D141: =F33 -> 0.0332
C142: % previsto acumulado | D142: =F35 -> 0.7742
C143: % executado acumulado | D143: =F37 -> 0.7589
B145: 01 | C145: Crédito do orçamento | D145: =F39 -> 16445090 | E145: =D145/$D$137 -> 0.7589
B146: 02 | C146: Saldo de contrato | D146: =F41 -> 0 | E146: =D146/$D$137 -> 0
B147: 03 | C147: Adiantamento de serviços não medidos | D147: =F43 -> 0 | E147: =D147/$D$137 -> 0
B148: 04 | C148: Adiantamento de materiais não estocados | D148: =F45 -> 0 | E148: =D148/$D$137 -> 0
B149: 05 | C149: Estoque de materiais | D149: =F47 -> 260170.11 | E149: =D149/$D$137 -> 0.012006204
B150: 06 | C150: Equipamentos (valor de mercado) | D150: =F49 -> 183300 | E150: =D150/$D$137 -> 0.0084588392
B151: 07 | C151: Receita de personalizações | D151: =F51 -> 434500 | E151: =D151/$D$137 -> 0.020051095
B152: 08 | C152: Contas a pagar dos medidos | D152: =F53 -> 151887.8 | E152: =D152/$D$137 -> 0.0070092443
B153: 09 | C153: Valor desembolsado (corrigido) | D153: =F56 -> 16752826 | E153: =D153/$D$137 -> 0.77310128
B154: 10 | C154: Dívida da obra a ser paga | D154: =F58 -> 0 | E154: =D154/$D$137 -> 0
C155: Resultado mensal da obra | D155: =D145+D146+D147+D148+D149+D150+D151-D152-D153-D154 -> 418345.64 | E155: =D155/D137 -> 0.019305611
C156: Resultado do mês anterior | D156: =NOV25!D155 -> 394440.32 | E156: =NOV25!E155 -> 0.018278253
B160: Significado de cada item
B162: Crédito do orçamento:
B163: Quanto a obra podia ter gasto pelo que executou: orçamento × executado acumulado.
B164: Saldo de contrato:
B165: Desconto obtido num contrato e ainda não realizado; abatido à medida que o serviço é medido.
B166: Adiantamento de serviços não medidos:
B167: Sinal pago de contrato ainda não medido (ex.: elevadores).
B168: Adiantamento de materiais não estocados:
B169: Material pago que ainda não chegou à obra (ex.: esquadrias).
B170: Estoque de materiais:
B171: Material no almoxarifado, ainda não aplicado, informado pelo almoxarife.
B172: Equipamentos (valor de mercado):
... B181: Material de outra obra da carteira usado nesta: custo da obra, desconta do resultado (versão 01 da planilha).

Sheet JAN26
B2: ANÁLISE DE DESEMPENHO ECONÔMICO DA OBRA
B3: Construtora fictícia de Natal/RN · portfólio Vizu Dados · dados inventados
B4: Versão 01 · revisão de 01/09/2025: a dívida da obra passa a descontar do resultado
B18: Célula editável
B19: Resultado (não editar)
B20: Tabela anexada
B21: % relacionada
B24: 1º passo: Projeto (definir o empreendimento) | D24: CAJUEIRO
B26: 2º passo: Mês de análise (definir o mês de referência) | E26: 46023
B28: 3º passo: Orçamento da obra projetado (com INCC no a realizar) | J28: 21759520
B29: Tipo do orçamento | J29: Orçamento final
B31: 4º passo: Previsto do mês (incluir o % do cronograma) | F31: 0.032
B33: 5º passo: Executado do mês (incluir o % medido) | F33: 0.0317
B35: 6º passo: Previsto acumulado do mês | F35: 0.8062
B37: 7º passo: Executado acumulado do mês | F37: 0.7906
B39: 8º passo: Crédito do orçamento (executado acumulado × orçamento) | F39: =F37*J28 -> 17203077
B41: 8º passo (cont.): Saldo de contrato (tabela) | F41: =E74 -> 0
B43: 9º passo: Adiantamento de serviços não medidos (tabela) | F43: =E88 -> 0
B45: 10º passo: Adiantamento de materiais não estocados (tabela) | F45: =J74 -> 0
B47: 11º passo: Estoque de materiais (almoxarifado) | F47: =J88 -> 302186.67
B49: 12º passo: Equipamentos comprados (valor de mercado) | F49: =E102 -> 183300
B51: 13º passo: Receitas de personalizações (tabela) | F51: =J102 -> 452000
B53: 14º passo: Contas a pagar dos medidos (relatório a pagar) | F53: =E115 -> 153622.69
B55: 15º passo: Valor desembolsado pela obra (relatório conferido) | F55: 17543844
B56: Valor corrigido (sem os itens apontados irregularmente) | F56: =F55-J115 -> 17543844
B58: 16º passo: Dívida da obra a ser paga (outra obra da carteira) | F58: =E129 -> 0
B63: Saldo de contrato | G63: Adiantamento de materiais não estocados
B74: Total | E74: =SUM(E64:E73) -> 0 | G74: Total | J74: =SUM(J64:J73) -> 0
B77: Adiantamento de serviços não medidos | G77: Estoque de materiais
G78: Blocos cerâmicos | J78: 60504.84
G79: Argamassa industrializada | J79: 51972.91
G80: Material hidrossanitário | J80: 76437.02
G81: Material elétrico (fios e cabos) | J81: 47176.25
G82: Revestimento cerâmico (compra antecipada) | J82: 66095.65
B88: Total | E88: =SUM(E78:E87) -> 0 | G88: Total | J88: =SUM(J78:J87) -> 302186.67
B91: Equipamentos comprados | G91: Receitas de personalizações
B92: Betoneira 400 L | E92: 9800 | G92: Unid. 501 · troca de piso da sala (cliente I. Moura) | J92: 120733.03
B93: Guincho de coluna | E93: 38500 | G93: Unid. 1603 · bancada da cozinha em quartzo (cliente J. Viana) | J93: 109230.54
B94: Andaime fachadeiro (lote) | E94: 64000 | G94: Unid. 401 · planta com home office (cliente K. Saraiva) | J94: 122825.08
B95: Plataforma elevatória | E95: 71000 | G95: Unid. 201 · ponto extra de ar-condicionado (cliente L. Fernandes) | J95: 99211.35
B102: Total | E102: =SUM(E92:E101) -> 183300 | G102: Total | J102: =SUM(J92:J101) -> 452000
B105: Contas a pagar dos medidos | G105: Itens apontados irregularmente no relatório
B106: Medição da empreiteira de alvenaria · NF 89644 | E106: 26810.57
B107: Medição de instalações hidráulicas · NF 92962 | E107: 45792.76
B108: Medição de instalações elétricas · NF 83589 | E108: 42966.12
B109: Encargos e INSS do mês · NF 94153 | E109: 38053.24
B115: Total | E115: =SUM(E106:E114) -> 153622.69 | G115: Total | J115: =SUM(J106:J114) -> 0
B118: Dívida da obra a ser paga
B129: Total | E129: =SUM(E119:E128) -> 0
B132: RESULTADO PARA UTILIZAR NA APRESENTAÇÃO
G135: Tabela informativa do desembolso do mês
C136: Projeto | D136: =D24 -> CAJUEIRO | G136: Valor previsto para o mês | J136: 858788.01
C137: Orçamento | D137: =J28 -> 21759520 | G137: Valor desembolsado no mês | J137: 791017.07
C138: Tipo do orçamento | D138: =J29 -> Orçamento final | G138: Diferença entre o previsto e o desembolsado | J138: =J137-J136 -> -67770.94
C139: Mês | D139: =E26 -> 46023 | G139: Justificativa para diferença acima de 10% (obrigatória)
C140: % previsto do mês | D140: =F31 -> 0.032
C141: % executado do mês | D141: =F33 -> 0.0317
C142: % previsto acumulado | D142: =F35 -> 0.8062
C143: % executado acumulado | D143: =F37 -> 0.7906
B145: 01 | C145: Crédito do orçamento | D145: =F39 -> 17203077 | E145: =D145/$D$137 -> 0.7906
B146: 02 | C146: Saldo de contrato | D146: =F41 -> 0 | E146: =D146/$D$137 -> 0
B147: 03 | C147: Adiantamento de serviços não medidos | D147: =F43 -> 0 | E147: =D147/$D$137 -> 0
B148: 04 | C148: Adiantamento de materiais não estocados | D148: =F45 -> 0 | E148: =D148/$D$137 -> 0
B149: 05 | C149: Estoque de materiais | D149: =F47 -> 302186.67 | E149: =D149/$D$137 -> 0.013887561
B150: 06 | C150: Equipamentos (valor de mercado) | D150: =F49 -> 183300 | E150: =D150/$D$137 -> 0.0084238991
B151: 07 | C151: Receita de personalizações | D151: =F51 -> 452000 | E151: =D151/$D$137 -> 0.020772517
B152: 08 | C152: Contas a pagar dos medidos | D152: =F53 -> 153622.69 | E152: =D152/$D$137 -> 0.007060022
B153: 09 | C153: Valor desembolsado (corrigido) | D153: =F56 -> 17543844 | E153: =D153/$D$137 -> 0.80626059
B154: 10 | C154: Dívida da obra a ser paga | D154: =F58 -> 0 | E154: =D154/$D$137 -> 0
C155: Resultado mensal da obra | D155: =D145+D146+D147+D148+D149+D150+D151-D152-D153-D154 -> 443096.95 | E155: =D155/D137 -> 0.020363361
C156: Resultado do mês anterior | D156: =DEZ25!D155 -> 418345.64 | E156: =DEZ25!E155 -> 0.019305611
B160: Significado de cada item
B162: Crédito do orçamento:
B163: Quanto a obra podia ter gasto pelo que executou: orçamento × executado acumulado.
B164: Saldo de contrato:
B165: Desconto obtido num contrato e ainda não realizado; abatido à medida que o serviço é medido.
B166: Adiantamento de serviços não medidos:
B167: Sinal pago de contrato ainda não medido (ex.: elevadores).
B168: Adiantamento de materiais não estocados:
B169: Material pago que ainda não chegou à obra (ex.: esquadrias).
B170: Estoque de materiais:
B171: Material no almoxarifado, ainda não aplicado, informado pelo almoxarife.
B172: Equipamentos (valor de mercado):
... B181: Material de outra obra da carteira usado nesta: custo da obra, desconta do resultado (versão 01 da planilha).

Sheet FEV26
B2: ANÁLISE DE DESEMPENHO ECONÔMICO DA OBRA
B3: Construtora fictícia de Natal/RN · portfólio Vizu Dados · dados inventados
B4: Versão 01 · revisão de 01/09/2025: a dívida da obra passa a descontar do resultado
B18: Célula editável
B19: Resultado (não editar)
B20: Tabela anexada
B21: % relacionada
B24: 1º passo: Projeto (definir o empreendimento) | D24: CAJUEIRO
B26: 2º passo: Mês de análise (definir o mês de referência) | E26: 46054
B28: 3º passo: Orçamento da obra projetado (com INCC no a realizar) | J28: 21849400
B29: Tipo do orçamento | J29: Orçamento final
B31: 4º passo: Previsto do mês (incluir o % do cronograma) | F31: 0.0303
B33: 5º passo: Executado do mês (incluir o % medido) | F33: 0.0291
B35: 6º passo: Previsto acumulado do mês | F35: 0.8365
B37: 7º passo: Executado acumulado do mês | F37: 0.8197
B39: 8º passo: Crédito do orçamento (executado acumulado × orçamento) | F39: =F37*J28 -> 17909953
B41: 8º passo (cont.): Saldo de contrato (tabela) | F41: =E74 -> 0
B43: 9º passo: Adiantamento de serviços não medidos (tabela) | F43: =E88 -> 0
B45: 10º passo: Adiantamento de materiais não estocados (tabela) | F45: =J74 -> 0
B47: 11º passo: Estoque de materiais (almoxarifado) | F47: =J88 -> 180829.82
B49: 12º passo: Equipamentos comprados (valor de mercado) | F49: =E102 -> 183300
B51: 13º passo: Receitas de personalizações (tabela) | F51: =J102 -> 469500
B53: 14º passo: Contas a pagar dos medidos (relatório a pagar) | F53: =E115 -> 135084.84
B55: 15º passo: Valor desembolsado pela obra (relatório conferido) | F55: 18140260
B56: Valor corrigido (sem os itens apontados irregularmente) | F56: =F55-J115 -> 18140260
B58: 16º passo: Dívida da obra a ser paga (outra obra da carteira) | F58: =E129 -> 0
B63: Saldo de contrato | G63: Adiantamento de materiais não estocados
B74: Total | E74: =SUM(E64:E73) -> 0 | G74: Total | J74: =SUM(J64:J73) -> 0
B77: Adiantamento de serviços não medidos | G77: Estoque de materiais
G78: Revestimento cerâmico interno | J78: 34606.4
G79: Porcelanato das áreas comuns | J79: 20762.94
G80: Louças e metais | J80: 18864.8
G81: Material elétrico (fios e cabos) | J81: 35425.8
G82: Tinta acrílica | J82: 32417.33
G83: Material para impermeabilização | J83: 38752.55
B88: Total | E88: =SUM(E78:E87) -> 0 | G88: Total | J88: =SUM(J78:J87) -> 180829.82
B91: Equipamentos comprados | G91: Receitas de personalizações
B92: Betoneira 400 L | E92: 9800 | G92: Unid. 501 · troca de piso da sala (cliente I. Moura) | J92: 125407.43
B93: Guincho de coluna | E93: 38500 | G93: Unid. 1603 · bancada da cozinha em quartzo (cliente J. Viana) | J93: 113459.59
B94: Andaime fachadeiro (lote) | E94: 64000 | G94: Unid. 401 · planta com home office (cliente K. Saraiva) | J94: 127580.48
B95: Plataforma elevatória | E95: 71000 | G95: Unid. 201 · ponto extra de ar-condicionado (cliente L. Fernandes) | J95: 103052.5
B102: Total | E102: =SUM(E92:E101) -> 183300 | G102: Total | J102: =SUM(J92:J101) -> 469500
B105: Contas a pagar dos medidos | G105: Itens apontados irregularmente no relatório
B106: Medição de reboco e gesso · NF 36307 | E106: 31936.68
B107: Medição de pintura · NF 96981 | E107: 28509.09
B108: Medição de revestimento · NF 90269 | E108: 27301.28
B109: Medição de instalações elétricas · NF 27008 | E109: 15277.06
B110: Encargos e INSS do mês · NF 96567 | E110: 32060.73
B115: Total | E115: =SUM(E106:E114) -> 135084.84 | G115: Total | J115: =SUM(J106:J114) -> 0
B118: Dívida da obra a ser paga
B129: Total | E129: =SUM(E119:E128) -> 0
B132: RESULTADO PARA UTILIZAR NA APRESENTAÇÃO
G135: Tabela informativa do desembolso do mês
C136: Projeto | D136: =D24 -> CAJUEIRO | G136: Valor previsto para o mês | J136: 622632.45
C137: Orçamento | D137: =J28 -> 21849400 | G137: Valor desembolsado no mês | J137: 596416.87
C138: Tipo do orçamento | D138: =J29 -> Orçamento final | G138: Diferença entre o previsto e o desembolsado | J138: =J137-J136 -> -26215.58
C139: Mês | D139: =E26 -> 46054 | G139: Justificativa para diferença acima de 10% (obrigatória)
C140: % previsto do mês | D140: =F31 -> 0.0303
C141: % executado do mês | D141: =F33 -> 0.0291
C142: % previsto acumulado | D142: =F35 -> 0.8365
C143: % executado acumulado | D143: =F37 -> 0.8197
B145: 01 | C145: Crédito do orçamento | D145: =F39 -> 17909953 | E145: =D145/$D$137 -> 0.8197
B146: 02 | C146: Saldo de contrato | D146: =F41 -> 0 | E146: =D146/$D$137 -> 0
B147: 03 | C147: Adiantamento de serviços não medidos | D147: =F43 -> 0 | E147: =D147/$D$137 -> 0
B148: 04 | C148: Adiantamento de materiais não estocados | D148: =F45 -> 0 | E148: =D148/$D$137 -> 0
B149: 05 | C149: Estoque de materiais | D149: =F47 -> 180829.82 | E149: =D149/$D$137 -> 0.0082761916
B150: 06 | C150: Equipamentos (valor de mercado) | D150: =F49 -> 183300 | E150: =D150/$D$137 -> 0.0083892464
B151: 07 | C151: Receita de personalizações | D151: =F51 -> 469500 | E151: =D151/$D$137 -> 0.021488004
B152: 08 | C152: Contas a pagar dos medidos | D152: =F53 -> 135084.84 | E152: =D152/$D$137 -> 0.0061825423
B153: 09 | C153: Valor desembolsado (corrigido) | D153: =F56 -> 18140260 | E153: =D153/$D$137 -> 0.83024067
B154: 10 | C154: Dívida da obra a ser paga | D154: =F58 -> 0 | E154: =D154/$D$137 -> 0
C155: Resultado mensal da obra | D155: =D145+D146+D147+D148+D149+D150+D151-D152-D153-D154 -> 468237.75 | E155: =D155/D137 -> 0.021430234
C156: Resultado do mês anterior | D156: =JAN26!D155 -> 443096.95 | E156: =JAN26!E155 -> 0.020363361
B160: Significado de cada item
B162: Crédito do orçamento:
B163: Quanto a obra podia ter gasto pelo que executou: orçamento × executado acumulado.
B164: Saldo de contrato:
B165: Desconto obtido num contrato e ainda não realizado; abatido à medida que o serviço é medido.
B166: Adiantamento de serviços não medidos:
B167: Sinal pago de contrato ainda não medido (ex.: elevadores).
B168: Adiantamento de materiais não estocados:
B169: Material pago que ainda não chegou à obra (ex.: esquadrias).
B170: Estoque de materiais:
B171: Material no almoxarifado, ainda não aplicado, informado pelo almoxarife.
B172: Equipamentos (valor de mercado):
... B181: Material de outra obra da carteira usado nesta: custo da obra, desconta do resultado (versão 01 da planilha).

Sheet MAR26
B2: ANÁLISE DE DESEMPENHO ECONÔMICO DA OBRA
B3: Construtora fictícia de Natal/RN · portfólio Vizu Dados · dados inventados
B4: Versão 01 · revisão de 01/09/2025: a dívida da obra passa a descontar do resultado
B18: Célula editável
B19: Resultado (não editar)
B20: Tabela anexada
B21: % relacionada
B24: 1º passo: Projeto (definir o empreendimento) | D24: CAJUEIRO
B26: 2º passo: Mês de análise (definir o mês de referência) | E26: 46082
B28: 3º passo: Orçamento da obra projetado (com INCC no a realizar) | J28: 21939280
B29: Tipo do orçamento | J29: Orçamento final
B31: 4º passo: Previsto do mês (incluir o % do cronograma) | F31: 0.0283
B33: 5º passo: Executado do mês (incluir o % medido) | F33: 0.028
B35: 6º passo: Previsto acumulado do mês | F35: 0.8648
B37: 7º passo: Executado acumulado do mês | F37: 0.8477
B39: 8º passo: Crédito do orçamento (executado acumulado × orçamento) | F39: =F37*J28 -> 18597928
B41: 8º passo (cont.): Saldo de contrato (tabela) | F41: =E74 -> 0
B43: 9º passo: Adiantamento de serviços não medidos (tabela) | F43: =E88 -> 0
B45: 10º passo: Adiantamento de materiais não estocados (tabela) | F45: =J74 -> 0
B47: 11º passo: Estoque de materiais (almoxarifado) | F47: =J88 -> 181531.32
B49: 12º passo: Equipamentos comprados (valor de mercado) | F49: =E102 -> 183300
B51: 13º passo: Receitas de personalizações (tabela) | F51: =J102 -> 487000
B53: 14º passo: Contas a pagar dos medidos (relatório a pagar) | F53: =E115 -> 150667.38
B55: 15º passo: Valor desembolsado pela obra (relatório conferido) | F55: 18804912
B56: Valor corrigido (sem os itens apontados irregularmente) | F56: =F55-J115 -> 18804912
B58: 16º passo: Dívida da obra a ser paga (outra obra da carteira) | F58: =E129 -> 0
B63: Saldo de contrato | G63: Adiantamento de materiais não estocados
B74: Total | E74: =SUM(E64:E73) -> 0 | G74: Total | J74: =SUM(J64:J73) -> 0
B77: Adiantamento de serviços não medidos | G77: Estoque de materiais
G78: Revestimento cerâmico interno | J78: 28765.73
G79: Porcelanato das áreas comuns | J79: 30209.69
G80: Louças e metais | J80: 28738.11
G81: Material elétrico (fios e cabos) | J81: 30441.33
G82: Tinta acrílica | J82: 34017.84
G83: Material para impermeabilização | J83: 29358.62
B88: Total | E88: =SUM(E78:E87) -> 0 | G88: Total | J88: =SUM(J78:J87) -> 181531.32
B91: Equipamentos comprados | G91: Receitas de personalizações
B92: Betoneira 400 L | E92: 9800 | G92: Unid. 501 · troca de piso da sala (cliente I. Moura) | J92: 109912.13
B93: Guincho de coluna | E93: 38500 | G93: Unid. 1603 · bancada da cozinha em quartzo (cliente J. Viana) | J93: 99440.57
B94: Andaime fachadeiro (lote) | E94: 64000 | G94: Unid. 401 · planta com home office (cliente K. Saraiva) | J94: 111816.68
B95: Plataforma elevatória | E95: 71000 | G95: Unid. 201 · ponto extra de ar-condicionado (cliente L. Fernandes) | J95: 90319.36
G96: Unid. 302 · revestimento da varanda (cliente M. Albuquerque) | J96: 75511.26
B102: Total | E102: =SUM(E92:E101) -> 183300 | G102: Total | J102: =SUM(J92:J101) -> 487000
B105: Contas a pagar dos medidos | G105: Itens apontados irregularmente no relatório
B106: Medição de reboco e gesso · NF 5553 | E106: 36917.03
B107: Medição de pintura · NF 3158 | E107: 24689.82
B108: Medição de revestimento · NF 90952 | E108: 27525.63
B109: Medição de instalações elétricas · NF 71443 | E109: 33318.65
B110: Encargos e INSS do mês · NF 48848 | E110: 28216.25
B115: Total | E115: =SUM(E106:E114) -> 150667.38 | G115: Total | J115: =SUM(J106:J114) -> 0
B118: Dívida da obra a ser paga
B129: Total | E129: =SUM(E119:E128) -> 0
B132: RESULTADO PARA UTILIZAR NA APRESENTAÇÃO
G135: Tabela informativa do desembolso do mês
C136: Projeto | D136: =D24 -> CAJUEIRO | G136: Valor previsto para o mês | J136: 667727.01
C137: Orçamento | D137: =J28 -> 21939280 | G137: Valor desembolsado no mês | J137: 664651.38
C138: Tipo do orçamento | D138: =J29 -> Orçamento final | G138: Diferença entre o previsto e o desembolsado | J138: =J137-J136 -> -3075.63
C139: Mês | D139: =E26 -> 46082 | G139: Justificativa para diferença acima de 10% (obrigatória)
C140: % previsto do mês | D140: =F31 -> 0.0283
C141: % executado do mês | D141: =F33 -> 0.028
C142: % previsto acumulado | D142: =F35 -> 0.8648
C143: % executado acumulado | D143: =F37 -> 0.8477
B145: 01 | C145: Crédito do orçamento | D145: =F39 -> 18597928 | E145: =D145/$D$137 -> 0.8477
B146: 02 | C146: Saldo de contrato | D146: =F41 -> 0 | E146: =D146/$D$137 -> 0
B147: 03 | C147: Adiantamento de serviços não medidos | D147: =F43 -> 0 | E147: =D147/$D$137 -> 0
B148: 04 | C148: Adiantamento de materiais não estocados | D148: =F45 -> 0 | E148: =D148/$D$137 -> 0
B149: 05 | C149: Estoque de materiais | D149: =F47 -> 181531.32 | E149: =D149/$D$137 -> 0.0082742606
B150: 06 | C150: Equipamentos (valor de mercado) | D150: =F49 -> 183300 | E150: =D150/$D$137 -> 0.0083548776
B151: 07 | C151: Receita de personalizações | D151: =F51 -> 487000 | E151: =D151/$D$137 -> 0.022197629
B152: 08 | C152: Contas a pagar dos medidos | D152: =F53 -> 150667.38 | E152: =D152/$D$137 -> 0.0068674715
B153: 09 | C153: Valor desembolsado (corrigido) | D153: =F56 -> 18804912 | E153: =D153/$D$137 -> 0.85713441
B154: 10 | C154: Dívida da obra a ser paga | D154: =F58 -> 0 | E154: =D154/$D$137 -> 0
C155: Resultado mensal da obra | D155: =D145+D146+D147+D148+D149+D150+D151-D152-D153-D154 -> 494179.81 | E155: =D155/D137 -> 0.022524887
C156: Resultado do mês anterior | D156: =FEV26!D155 -> 468237.75 | E156: =FEV26!E155 -> 0.021430234
B160: Significado de cada item
B162: Crédito do orçamento:
B163: Quanto a obra podia ter gasto pelo que executou: orçamento × executado acumulado.
B164: Saldo de contrato:
B165: Desconto obtido num contrato e ainda não realizado; abatido à medida que o serviço é medido.
B166: Adiantamento de serviços não medidos:
B167: Sinal pago de contrato ainda não medido (ex.: elevadores).
B168: Adiantamento de materiais não estocados:
B169: Material pago que ainda não chegou à obra (ex.: esquadrias).
B170: Estoque de materiais:
B171: Material no almoxarifado, ainda não aplicado, informado pelo almoxarife.
B172: Equipamentos (valor de mercado):
... B181: Material de outra obra da carteira usado nesta: custo da obra, desconta do resultado (versão 01 da planilha).

Sheet ABR26
B2: ANÁLISE DE DESEMPENHO ECONÔMICO DA OBRA
B3: Construtora fictícia de Natal/RN · portfólio Vizu Dados · dados inventados
B4: Versão 01 · revisão de 01/09/2025: a dívida da obra passa a descontar do resultado
B18: Célula editável
B19: Resultado (não editar)
B20: Tabela anexada
B21: % relacionada
B24: 1º passo: Projeto (definir o empreendimento) | D24: CAJUEIRO
B26: 2º passo: Mês de análise (definir o mês de referência) | E26: 46113
B28: 3º passo: Orçamento da obra projetado (com INCC no a realizar) | J28: 22029160
B29: Tipo do orçamento | J29: Orçamento final
B31: 4º passo: Previsto do mês (incluir o % do cronograma) | F31: 0.0262
B33: 5º passo: Executado do mês (incluir o % medido) | F33: 0.0252
B35: 6º passo: Previsto acumulado do mês | F35: 0.891
B37: 7º passo: Executado acumulado do mês | F37: 0.8729
B39: 8º passo: Crédito do orçamento (executado acumulado × orçamento) | F39: =F37*J28 -> 19229254
B41: 8º passo (cont.): Saldo de contrato (tabela) | F41: =E74 -> 0
B43: 9º passo: Adiantamento de serviços não medidos (tabela) | F43: =E88 -> 0
B45: 10º passo: Adiantamento de materiais não estocados (tabela) | F45: =J74 -> 0
B47: 11º passo: Estoque de materiais (almoxarifado) | F47: =J88 -> 216114.16
B49: 12º passo: Equipamentos comprados (valor de mercado) | F49: =E102 -> 183300
B51: 13º passo: Receitas de personalizações (tabela) | F51: =J102 -> 504500
B53: 14º passo: Contas a pagar dos medidos (relatório a pagar) | F53: =E115 -> 112131.97
B55: 15º passo: Valor desembolsado pela obra (relatório conferido) | F55: 19522502
B56: Valor corrigido (sem os itens apontados irregularmente) | F56: =F55-J115 -> 19522502
B58: 16º passo: Dívida da obra a ser paga (outra obra da carteira) | F58: =E129 -> 0
B63: Saldo de contrato | G63: Adiantamento de materiais não estocados
B74: Total | E74: =SUM(E64:E73) -> 0 | G74: Total | J74: =SUM(J64:J73) -> 0
B77: Adiantamento de serviços não medidos | G77: Estoque de materiais
G78: Revestimento cerâmico interno | J78: 28725.62
G79: Porcelanato das áreas comuns | J79: 46064.94
G80: Louças e metais | J80: 33191.72
G81: Material elétrico (fios e cabos) | J81: 24974.82
G82: Tinta acrílica | J82: 42241.78
G83: Material para impermeabilização | J83: 40915.28
B88: Total | E88: =SUM(E78:E87) -> 0 | G88: Total | J88: =SUM(J78:J87) -> 216114.16
B91: Equipamentos comprados | G91: Receitas de personalizações
B92: Betoneira 400 L | E92: 9800 | G92: Unid. 501 · troca de piso da sala (cliente I. Moura) | J92: 113861.75
B93: Guincho de coluna | E93: 38500 | G93: Unid. 1603 · bancada da cozinha em quartzo (cliente J. Viana) | J93: 103013.89
B94: Andaime fachadeiro (lote) | E94: 64000 | G94: Unid. 401 · planta com home office (cliente K. Saraiva) | J94: 115834.73
B95: Plataforma elevatória | E95: 71000 | G95: Unid. 201 · ponto extra de ar-condicionado (cliente L. Fernandes) | J95: 93564.93
G96: Unid. 302 · revestimento da varanda (cliente M. Albuquerque) | J96: 78224.7
B102: Total | E102: =SUM(E92:E101) -> 183300 | G102: Total | J102: =SUM(J92:J101) -> 504500
B105: Contas a pagar dos medidos | G105: Itens apontados irregularmente no relatório
B106: Medição de reboco e gesso · NF 81547 | E106: 23211.59
B107: Medição de pintura · NF 83102 | E107: 18927.94
B108: Medição de revestimento · NF 78394 | E108: 20267.77
B109: Medição de instalações elétricas · NF 73291 | E109: 25103.74
B110: Encargos e INSS do mês · NF 35631 | E110: 24620.93
B115: Total | E115: =SUM(E106:E114) -> 112131.97 | G115: Total | J115: =SUM(J106:J114) -> 0
B118: Dívida da obra a ser paga
B129: Total | E129: =SUM(E119:E128) -> 0
B132: RESULTADO PARA UTILIZAR NA APRESENTAÇÃO
G135: Tabela informativa do desembolso do mês
C136: Projeto | D136: =D24 -> CAJUEIRO | G136: Valor previsto para o mês | J136: 696245.72
C137: Orçamento | D137: =J28 -> 22029160 | G137: Valor desembolsado no mês | J137: 717590.49
C138: Tipo do orçamento | D138: =J29 -> Orçamento final | G138: Diferença entre o previsto e o desembolsado | J138: =J137-J136 -> 21344.77
C139: Mês | D139: =E26 -> 46113 | G139: Justificativa para diferença acima de 10% (obrigatória)
C140: % previsto do mês | D140: =F31 -> 0.0262
C141: % executado do mês | D141: =F33 -> 0.0252
C142: % previsto acumulado | D142: =F35 -> 0.891
C143: % executado acumulado | D143: =F37 -> 0.8729
B145: 01 | C145: Crédito do orçamento | D145: =F39 -> 19229254 | E145: =D145/$D$137 -> 0.8729
B146: 02 | C146: Saldo de contrato | D146: =F41 -> 0 | E146: =D146/$D$137 -> 0
B147: 03 | C147: Adiantamento de serviços não medidos | D147: =F43 -> 0 | E147: =D147/$D$137 -> 0
B148: 04 | C148: Adiantamento de materiais não estocados | D148: =F45 -> 0 | E148: =D148/$D$137 -> 0
B149: 05 | C149: Estoque de materiais | D149: =F47 -> 216114.16 | E149: =D149/$D$137 -> 0.0098103677
B150: 06 | C150: Equipamentos (valor de mercado) | D150: =F49 -> 183300 | E150: =D150/$D$137 -> 0.0083207894
B151: 07 | C151: Receita de personalizações | D151: =F51 -> 504500 | E151: =D151/$D$137 -> 0.022901463
B152: 08 | C152: Contas a pagar dos medidos | D152: =F53 -> 112131.97 | E152: =D152/$D$137 -> 0.005090161
B153: 09 | C153: Valor desembolsado (corrigido) | D153: =F56 -> 19522502 | E153: =D153/$D$137 -> 0.88621183
B154: 10 | C154: Dívida da obra a ser paga | D154: =F58 -> 0 | E154: =D154/$D$137 -> 0
C155: Resultado mensal da obra | D155: =D145+D146+D147+D148+D149+D150+D151-D152-D153-D154 -> 498533.67 | E155: =D155/D137 -> 0.022630626
C156: Resultado do mês anterior | D156: =MAR26!D155 -> 494179.81 | E156: =MAR26!E155 -> 0.022524887
B160: Significado de cada item
B162: Crédito do orçamento:
B163: Quanto a obra podia ter gasto pelo que executou: orçamento × executado acumulado.
B164: Saldo de contrato:
B165: Desconto obtido num contrato e ainda não realizado; abatido à medida que o serviço é medido.
B166: Adiantamento de serviços não medidos:
B167: Sinal pago de contrato ainda não medido (ex.: elevadores).
B168: Adiantamento de materiais não estocados:
B169: Material pago que ainda não chegou à obra (ex.: esquadrias).
B170: Estoque de materiais:
B171: Material no almoxarifado, ainda não aplicado, informado pelo almoxarife.
B172: Equipamentos (valor de mercado):
... B181: Material de outra obra da carteira usado nesta: custo da obra, desconta do resultado (versão 01 da planilha).

Sheet MAI26
B2: ANÁLISE DE DESEMPENHO ECONÔMICO DA OBRA
B3: Construtora fictícia de Natal/RN · portfólio Vizu Dados · dados inventados
B4: Versão 01 · revisão de 01/09/2025: a dívida da obra passa a descontar do resultado
B18: Célula editável
B19: Resultado (não editar)
B20: Tabela anexada
B21: % relacionada
B24: 1º passo: Projeto (definir o empreendimento) | D24: CAJUEIRO
B26: 2º passo: Mês de análise (definir o mês de referência) | E26: 46143
B28: 3º passo: Orçamento da obra projetado (com INCC no a realizar) | J28: 22119040
B29: Tipo do orçamento | J29: Orçamento final
B31: 4º passo: Previsto do mês (incluir o % do cronograma) | F31: 0.0239
B33: 5º passo: Executado do mês (incluir o % medido) | F33: 0.0237
B35: 6º passo: Previsto acumulado do mês | F35: 0.9149
B37: 7º passo: Executado acumulado do mês | F37: 0.8966
B39: 8º passo: Crédito do orçamento (executado acumulado × orçamento) | F39: =F37*J28 -> 19831931
B41: 8º passo (cont.): Saldo de contrato (tabela) | F41: =E74 -> 0
B43: 9º passo: Adiantamento de serviços não medidos (tabela) | F43: =E88 -> 0
B45: 10º passo: Adiantamento de materiais não estocados (tabela) | F45: =J74 -> 0
B47: 11º passo: Estoque de materiais (almoxarifado) | F47: =J88 -> 217652.63
B49: 12º passo: Equipamentos comprados (valor de mercado) | F49: =E102 -> 183300
B51: 13º passo: Receitas de personalizações (tabela) | F51: =J102 -> 522000
B53: 14º passo: Contas a pagar dos medidos (relatório a pagar) | F53: =E115 -> 126255.97
B55: 15º passo: Valor desembolsado pela obra (relatório conferido) | F55: 20126612
B56: Valor corrigido (sem os itens apontados irregularmente) | F56: =F55-J115 -> 20126612
B58: 16º passo: Dívida da obra a ser paga (outra obra da carteira) | F58: =E129 -> 0
B63: Saldo de contrato | G63: Adiantamento de materiais não estocados
B74: Total | E74: =SUM(E64:E73) -> 0 | G74: Total | J74: =SUM(J64:J73) -> 0
B77: Adiantamento de serviços não medidos | G77: Estoque de materiais
G78: Revestimento cerâmico interno | J78: 24734.13
G79: Porcelanato das áreas comuns | J79: 32918.92
G80: Louças e metais | J80: 47111.9
G81: Material elétrico (fios e cabos) | J81: 43920.09
G82: Tinta acrílica | J82: 27087.34
G83: Material para impermeabilização | J83: 41880.25
B88: Total | E88: =SUM(E78:E87) -> 0 | G88: Total | J88: =SUM(J78:J87) -> 217652.63
B91: Equipamentos comprados | G91: Receitas de personalizações
B92: Betoneira 400 L | E92: 9800 | G92: Unid. 501 · troca de piso da sala (cliente I. Moura) | J92: 97831.71
B93: Guincho de coluna | E93: 38500 | G93: Unid. 1603 · bancada da cozinha em quartzo (cliente J. Viana) | J93: 88511.07
B94: Andaime fachadeiro (lote) | E94: 64000 | G94: Unid. 401 · planta com home office (cliente K. Saraiva) | J94: 99526.93
B95: Plataforma elevatória | E95: 71000 | G95: Unid. 201 · ponto extra de ar-condicionado (cliente L. Fernandes) | J95: 80392.38
G96: Unid. 302 · revestimento da varanda (cliente M. Albuquerque) | J96: 67211.83
G97: Unid. 1302 · fechamento da cozinha (cliente N. Siqueira) | J97: 88526.08
B102: Total | E102: =SUM(E92:E101) -> 183300 | G102: Total | J102: =SUM(J92:J101) -> 522000
B105: Contas a pagar dos medidos | G105: Itens apontados irregularmente no relatório
B106: Medição de reboco e gesso · NF 29277 | E106: 19950.16
B107: Medição de pintura · NF 86518 | E107: 28868.94
B108: Medição de revestimento · NF 32060 | E108: 29563.11
B109: Medição de instalações elétricas · NF 6258 | E109: 17483.45
B110: Encargos e INSS do mês · NF 13129 | E110: 30390.31
B115: Total | E115: =SUM(E106:E114) -> 126255.97 | G115: Total | J115: =SUM(J106:J114) -> 0
B118: Dívida da obra a ser paga
B129: Total | E129: =SUM(E119:E128) -> 0
B132: RESULTADO PARA UTILIZAR NA APRESENTAÇÃO
G135: Tabela informativa do desembolso do mês
C136: Projeto | D136: =D24 -> CAJUEIRO | G136: Valor previsto para o mês | J136: 559649.93
C137: Orçamento | D137: =J28 -> 22119040 | G137: Valor desembolsado no mês | J137: 604109.79
C138: Tipo do orçamento | D138: =J29 -> Orçamento final | G138: Diferença entre o previsto e o desembolsado | J138: =J137-J136 -> 44459.86
C139: Mês | D139: =E26 -> 46143 | G139: Justificativa para diferença acima de 10% (obrigatória)
C140: % previsto do mês | D140: =F31 -> 0.0239
C141: % executado do mês | D141: =F33 -> 0.0237
C142: % previsto acumulado | D142: =F35 -> 0.9149
C143: % executado acumulado | D143: =F37 -> 0.8966
B145: 01 | C145: Crédito do orçamento | D145: =F39 -> 19831931 | E145: =D145/$D$137 -> 0.8966
B146: 02 | C146: Saldo de contrato | D146: =F41 -> 0 | E146: =D146/$D$137 -> 0
B147: 03 | C147: Adiantamento de serviços não medidos | D147: =F43 -> 0 | E147: =D147/$D$137 -> 0
B148: 04 | C148: Adiantamento de materiais não estocados | D148: =F45 -> 0 | E148: =D148/$D$137 -> 0
B149: 05 | C149: Estoque de materiais | D149: =F47 -> 217652.63 | E149: =D149/$D$137 -> 0.0098400577
B150: 06 | C150: Equipamentos (valor de mercado) | D150: =F49 -> 183300 | E150: =D150/$D$137 -> 0.0082869781
B151: 07 | C151: Receita de personalizações | D151: =F51 -> 522000 | E151: =D151/$D$137 -> 0.023599578
B152: 08 | C152: Contas a pagar dos medidos | D152: =F53 -> 126255.97 | E152: =D152/$D$137 -> 0.0057080221
B153: 09 | C153: Valor desembolsado (corrigido) | D153: =F56 -> 20126612 | E153: =D153/$D$137 -> 0.9099225
B154: 10 | C154: Dívida da obra a ser paga | D154: =F58 -> 0 | E154: =D154/$D$137 -> 0
C155: Resultado mensal da obra | D155: =D145+D146+D147+D148+D149+D150+D151-D152-D153-D154 -> 502015.85 | E155: =D155/D137 -> 0.022696096
C156: Resultado do mês anterior | D156: =ABR26!D155 -> 498533.67 | E156: =ABR26!E155 -> 0.022630626
B160: Significado de cada item
B162: Crédito do orçamento:
B163: Quanto a obra podia ter gasto pelo que executou: orçamento × executado acumulado.
B164: Saldo de contrato:
B165: Desconto obtido num contrato e ainda não realizado; abatido à medida que o serviço é medido.
B166: Adiantamento de serviços não medidos:
B167: Sinal pago de contrato ainda não medido (ex.: elevadores).
B168: Adiantamento de materiais não estocados:
B169: Material pago que ainda não chegou à obra (ex.: esquadrias).
B170: Estoque de materiais:
B171: Material no almoxarifado, ainda não aplicado, informado pelo almoxarife.
B172: Equipamentos (valor de mercado):
... B181: Material de outra obra da carteira usado nesta: custo da obra, desconta do resultado (versão 01 da planilha).

Sheet JUN26
B2: ANÁLISE DE DESEMPENHO ECONÔMICO DA OBRA
B3: Construtora fictícia de Natal/RN · portfólio Vizu Dados · dados inventados
B4: Versão 01 · revisão de 01/09/2025: a dívida da obra passa a descontar do resultado
B18: Célula editável
B19: Resultado (não editar)
B20: Tabela anexada
B21: % relacionada
B24: 1º passo: Projeto (definir o empreendimento) | D24: CAJUEIRO
B26: 2º passo: Mês de análise (definir o mês de referência) | E26: 46174
B28: 3º passo: Orçamento da obra projetado (com INCC no a realizar) | J28: 22208920
B29: Tipo do orçamento | J29: Orçamento final
B31: 4º passo: Previsto do mês (incluir o % do cronograma) | F31: 0.0214
B33: 5º passo: Executado do mês (incluir o % medido) | F33: 0.0219
B35: 6º passo: Previsto acumulado do mês | F35: 0.9363
B37: 7º passo: Executado acumulado do mês | F37: 0.9185
B39: 8º passo: Crédito do orçamento (executado acumulado × orçamento) | F39: =F37*J28 -> 20398893
B41: 8º passo (cont.): Saldo de contrato (tabela) | F41: =E74 -> 0
B43: 9º passo: Adiantamento de serviços não medidos (tabela) | F43: =E88 -> 0
B45: 10º passo: Adiantamento de materiais não estocados (tabela) | F45: =J74 -> 0
B47: 11º passo: Estoque de materiais (almoxarifado) | F47: =J88 -> 190387.92
B49: 12º passo: Equipamentos comprados (valor de mercado) | F49: =E102 -> 183300
B51: 13º passo: Receitas de personalizações (tabela) | F51: =J102 -> 539500
B53: 14º passo: Contas a pagar dos medidos (relatório a pagar) | F53: =E115 -> 91273.27
B55: 15º passo: Valor desembolsado pela obra (relatório conferido) | F55: 20716265
B56: Valor corrigido (sem os itens apontados irregularmente) | F56: =F55-J115 -> 20716265
B58: 16º passo: Dívida da obra a ser paga (outra obra da carteira) | F58: =E129 -> 0
B63: Saldo de contrato | G63: Adiantamento de materiais não estocados
B74: Total | E74: =SUM(E64:E73) -> 0 | G74: Total | J74: =SUM(J64:J73) -> 0
B77: Adiantamento de serviços não medidos | G77: Estoque de materiais
G78: Revestimento cerâmico interno | J78: 33104.49
G79: Porcelanato das áreas comuns | J79: 36778.08
G80: Louças e metais | J80: 21266.64
G81: Material elétrico (fios e cabos) | J81: 26071.12
G82: Tinta acrílica | J82: 35901.11
G83: Material para impermeabilização | J83: 37266.48
B88: Total | E88: =SUM(E78:E87) -> 0 | G88: Total | J88: =SUM(J78:J87) -> 190387.92
B91: Equipamentos comprados | G91: Receitas de personalizações
B92: Betoneira 400 L | E92: 9800 | G92: Unid. 501 · troca de piso da sala (cliente I. Moura) | J92: 101111.51
B93: Guincho de coluna | E93: 38500 | G93: Unid. 1603 · bancada da cozinha em quartzo (cliente J. Viana) | J93: 91478.4
B94: Andaime fachadeiro (lote) | E94: 64000 | G94: Unid. 401 · planta com home office (cliente K. Saraiva) | J94: 102863.56
B95: Plataforma elevatória | E95: 71000 | G95: Unid. 201 · ponto extra de ar-condicionado (cliente L. Fernandes) | J95: 83087.53
G96: Unid. 302 · revestimento da varanda (cliente M. Albuquerque) | J96: 69465.1
G97: Unid. 1302 · fechamento da cozinha (cliente N. Siqueira) | J97: 91493.9
B102: Total | E102: =SUM(E92:E101) -> 183300 | G102: Total | J102: =SUM(J92:J101) -> 539500
B105: Contas a pagar dos medidos | G105: Itens apontados irregularmente no relatório
B106: Medição de reboco e gesso · NF 92721 | E106: 23899.27
B107: Medição de pintura · NF 78201 | E107: 15864.55
B108: Medição de revestimento · NF 82046 | E108: 20829.78
B109: Medição de instalações elétricas · NF 96502 | E109: 18247.54
B110: Encargos e INSS do mês · NF 59799 | E110: 12432.13
B115: Total | E115: =SUM(E106:E114) -> 91273.27 | G115: Total | J115: =SUM(J106:J114) -> 0
B118: Dívida da obra a ser paga
B129: Total | E129: =SUM(E119:E128) -> 0
B132: RESULTADO PARA UTILIZAR NA APRESENTAÇÃO
G135: Tabela informativa do desembolso do mês
C136: Projeto | D136: =D24 -> CAJUEIRO | G136: Valor previsto para o mês | J136: 564393.3
C137: Orçamento | D137: =J28 -> 22208920 | G137: Valor desembolsado no mês | J137: 589653.19
C138: Tipo do orçamento | D138: =J29 -> Orçamento final | G138: Diferença entre o previsto e o desembolsado | J138: =J137-J136 -> 25259.89
C139: Mês | D139: =E26 -> 46174 | G139: Justificativa para diferença acima de 10% (obrigatória)
C140: % previsto do mês | D140: =F31 -> 0.0214
C141: % executado do mês | D141: =F33 -> 0.0219
C142: % previsto acumulado | D142: =F35 -> 0.9363
C143: % executado acumulado | D143: =F37 -> 0.9185
B145: 01 | C145: Crédito do orçamento | D145: =F39 -> 20398893 | E145: =D145/$D$137 -> 0.9185
B146: 02 | C146: Saldo de contrato | D146: =F41 -> 0 | E146: =D146/$D$137 -> 0
B147: 03 | C147: Adiantamento de serviços não medidos | D147: =F43 -> 0 | E147: =D147/$D$137 -> 0
B148: 04 | C148: Adiantamento de materiais não estocados | D148: =F45 -> 0 | E148: =D148/$D$137 -> 0
B149: 05 | C149: Estoque de materiais | D149: =F47 -> 190387.92 | E149: =D149/$D$137 -> 0.008572588
B150: 06 | C150: Equipamentos (valor de mercado) | D150: =F49 -> 183300 | E150: =D150/$D$137 -> 0.0082534405
B151: 07 | C151: Receita de personalizações | D151: =F51 -> 539500 | E151: =D151/$D$137 -> 0.024292041
B152: 08 | C152: Contas a pagar dos medidos | D152: =F53 -> 91273.27 | E152: =D152/$D$137 -> 0.0041097573
B153: 09 | C153: Valor desembolsado (corrigido) | D153: =F56 -> 20716265 | E153: =D153/$D$137 -> 0.9327903
B154: 10 | C154: Dívida da obra a ser paga | D154: =F58 -> 0 | E154: =D154/$D$137 -> 0
C155: Resultado mensal da obra | D155: =D145+D146+D147+D148+D149+D150+D151-D152-D153-D154 -> 504542.41 | E155: =D155/D137 -> 0.022718007
C156: Resultado do mês anterior | D156: =MAI26!D155 -> 502015.85 | E156: =MAI26!E155 -> 0.022696096
B160: Significado de cada item
B162: Crédito do orçamento:
B163: Quanto a obra podia ter gasto pelo que executou: orçamento × executado acumulado.
B164: Saldo de contrato:
B165: Desconto obtido num contrato e ainda não realizado; abatido à medida que o serviço é medido.
B166: Adiantamento de serviços não medidos:
B167: Sinal pago de contrato ainda não medido (ex.: elevadores).
B168: Adiantamento de materiais não estocados:
B169: Material pago que ainda não chegou à obra (ex.: esquadrias).
B170: Estoque de materiais:
B171: Material no almoxarifado, ainda não aplicado, informado pelo almoxarife.
B172: Equipamentos (valor de mercado):
... B181: Material de outra obra da carteira usado nesta: custo da obra, desconta do resultado (versão 01 da planilha).

Sheet JUL26
B2: ANÁLISE DE DESEMPENHO ECONÔMICO DA OBRA
B3: Construtora fictícia de Natal/RN · portfólio Vizu Dados · dados inventados
B4: Versão 01 · revisão de 01/09/2025: a dívida da obra passa a descontar do resultado
B18: Célula editável
B19: Resultado (não editar)
B20: Tabela anexada
B21: % relacionada
B24: 1º passo: Projeto (definir o empreendimento) | D24: CAJUEIRO
B26: 2º passo: Mês de análise (definir o mês de referência) | E26: 46204
B28: 3º passo: Orçamento da obra projetado (com INCC no a realizar) | J28: 22298800
B29: Tipo do orçamento | J29: Orçamento final
B31: 4º passo: Previsto do mês (incluir o % do cronograma) | F31: 0.0186
B33: 5º passo: Executado do mês (incluir o % medido) | F33: 0.0197
B35: 6º passo: Previsto acumulado do mês | F35: 0.9549
B37: 7º passo: Executado acumulado do mês | F37: 0.9382
B39: 8º passo: Crédito do orçamento (executado acumulado × orçamento) | F39: =F37*J28 -> 20920734
B41: 8º passo (cont.): Saldo de contrato (tabela) | F41: =E74 -> 0
B43: 9º passo: Adiantamento de serviços não medidos (tabela) | F43: =E88 -> 0
B45: 10º passo: Adiantamento de materiais não estocados (tabela) | F45: =J74 -> 0
B47: 11º passo: Estoque de materiais (almoxarifado) | F47: =J88 -> 220847.31
B49: 12º passo: Equipamentos comprados (valor de mercado) | F49: =E102 -> 183300
B51: 13º passo: Receitas de personalizações (tabela) | F51: =J102 -> 557000
B53: 14º passo: Contas a pagar dos medidos (relatório a pagar) | F53: =E115 -> 85706.45
B55: 15º passo: Valor desembolsado pela obra (relatório conferido) | F55: 21290173
B56: Valor corrigido (sem os itens apontados irregularmente) | F56: =F55-J115 -> 21290173
B58: 16º passo: Dívida da obra a ser paga (outra obra da carteira) | F58: =E129 -> 0
B63: Saldo de contrato | G63: Adiantamento de materiais não estocados
B74: Total | E74: =SUM(E64:E73) -> 0 | G74: Total | J74: =SUM(J64:J73) -> 0
B77: Adiantamento de serviços não medidos | G77: Estoque de materiais
G78: Revestimento cerâmico interno | J78: 43706.24
G79: Porcelanato das áreas comuns | J79: 25781.31
G80: Louças e metais | J80: 34372.29
G81: Material elétrico (fios e cabos) | J81: 33673.58
G82: Tinta acrílica | J82: 54260.27
G83: Material para impermeabilização | J83: 29053.62
B88: Total | E88: =SUM(E78:E87) -> 0 | G88: Total | J88: =SUM(J78:J87) -> 220847.31
B91: Equipamentos comprados | G91: Receitas de personalizações
B92: Betoneira 400 L | E92: 9800 | G92: Unid. 501 · troca de piso da sala (cliente I. Moura) | J92: 85730.76
B93: Guincho de coluna | E93: 38500 | G93: Unid. 1603 · bancada da cozinha em quartzo (cliente J. Viana) | J93: 77563.01
B94: Andaime fachadeiro (lote) | E94: 64000 | G94: Unid. 401 · planta com home office (cliente K. Saraiva) | J94: 87216.29
B95: Plataforma elevatória | E95: 71000 | G95: Unid. 201 · ponto extra de ar-condicionado (cliente L. Fernandes) | J95: 70448.53
G96: Unid. 302 · revestimento da varanda (cliente M. Albuquerque) | J96: 58898.3
G97: Unid. 1302 · fechamento da cozinha (cliente N. Siqueira) | J97: 77576.15
G98: Unid. 1104 · box e metais de padrão superior (cliente A. Cavalcanti) | J98: 99566.96
B102: Total | E102: =SUM(E92:E101) -> 183300 | G102: Total | J102: =SUM(J92:J101) -> 557000
B105: Contas a pagar dos medidos | G105: Itens apontados irregularmente no relatório
B106: Medição de reboco e gesso · NF 28008 | E106: 10932.37
B107: Medição de pintura · NF 74931 | E107: 15009.36
B108: Medição de revestimento · NF 27266 | E108: 19245.01
B109: Medição de instalações elétricas · NF 17874 | E109: 20790.92
B110: Encargos e INSS do mês · NF 26904 | E110: 19728.79
B115: Total | E115: =SUM(E106:E114) -> 85706.45 | G115: Total | J115: =SUM(J106:J114) -> 0
B118: Dívida da obra a ser paga
B129: Total | E129: =SUM(E119:E128) -> 0
B132: RESULTADO PARA UTILIZAR NA APRESENTAÇÃO
G135: Tabela informativa do desembolso do mês
C136: Projeto | D136: =D24 -> CAJUEIRO | G136: Valor previsto para o mês | J136: 557916.62
C137: Orçamento | D137: =J28 -> 22298800 | G137: Valor desembolsado no mês | J137: 573907.26
C138: Tipo do orçamento | D138: =J29 -> Orçamento final | G138: Diferença entre o previsto e o desembolsado | J138: =J137-J136 -> 15990.64
C139: Mês | D139: =E26 -> 46204 | G139: Justificativa para diferença acima de 10% (obrigatória)
C140: % previsto do mês | D140: =F31 -> 0.0186
C141: % executado do mês | D141: =F33 -> 0.0197
C142: % previsto acumulado | D142: =F35 -> 0.9549
C143: % executado acumulado | D143: =F37 -> 0.9382
B145: 01 | C145: Crédito do orçamento | D145: =F39 -> 20920734 | E145: =D145/$D$137 -> 0.9382
B146: 02 | C146: Saldo de contrato | D146: =F41 -> 0 | E146: =D146/$D$137 -> 0
B147: 03 | C147: Adiantamento de serviços não medidos | D147: =F43 -> 0 | E147: =D147/$D$137 -> 0
B148: 04 | C148: Adiantamento de materiais não estocados | D148: =F45 -> 0 | E148: =D148/$D$137 -> 0
B149: 05 | C149: Estoque de materiais | D149: =F47 -> 220847.31 | E149: =D149/$D$137 -> 0.0099039998
B150: 06 | C150: Equipamentos (valor de mercado) | D150: =F49 -> 183300 | E150: =D150/$D$137 -> 0.0082201733
B151: 07 | C151: Receita de personalizações | D151: =F51 -> 557000 | E151: =D151/$D$137 -> 0.024978923
B152: 08 | C152: Contas a pagar dos medidos | D152: =F53 -> 85706.45 | E152: =D152/$D$137 -> 0.0038435454
B153: 09 | C153: Valor desembolsado (corrigido) | D153: =F56 -> 21290173 | E153: =D153/$D$137 -> 0.95476763
B154: 10 | C154: Dívida da obra a ser paga | D154: =F58 -> 0 | E154: =D154/$D$137 -> 0
C155: Resultado mensal da obra | D155: =D145+D146+D147+D148+D149+D150+D151-D152-D153-D154 -> 506002.5 | E155: =D155/D137 -> 0.022691916
C156: Resultado do mês anterior | D156: =JUN26!D155 -> 504542.41 | E156: =JUN26!E155 -> 0.022718007
B160: Significado de cada item
B162: Crédito do orçamento:
B163: Quanto a obra podia ter gasto pelo que executou: orçamento × executado acumulado.
B164: Saldo de contrato:
B165: Desconto obtido num contrato e ainda não realizado; abatido à medida que o serviço é medido.
B166: Adiantamento de serviços não medidos:
B167: Sinal pago de contrato ainda não medido (ex.: elevadores).
B168: Adiantamento de materiais não estocados:
B169: Material pago que ainda não chegou à obra (ex.: esquadrias).
B170: Estoque de materiais:
B171: Material no almoxarifado, ainda não aplicado, informado pelo almoxarife.
B172: Equipamentos (valor de mercado):
... B181: Material de outra obra da carteira usado nesta: custo da obra, desconta do resultado (versão 01 da planilha).

Sheet AGO26
B2: ANÁLISE DE DESEMPENHO ECONÔMICO DA OBRA
B3: Construtora fictícia de Natal/RN · portfólio Vizu Dados · dados inventados
B4: Versão 01 · revisão de 01/09/2025: a dívida da obra passa a descontar do resultado
B18: Célula editável
B19: Resultado (não editar)
B20: Tabela anexada
B21: % relacionada
B24: 1º passo: Projeto (definir o empreendimento) | D24: CAJUEIRO
B26: 2º passo: Mês de análise (definir o mês de referência) | E26: 46235
B28: 3º passo: Orçamento da obra projetado (com INCC no a realizar) | J28: 22388680
B29: Tipo do orçamento | J29: Orçamento final
B31: 4º passo: Previsto do mês (incluir o % do cronograma) | F31: 0.0157
B33: 5º passo: Executado do mês (incluir o % medido) | F33: 0.0202
B35: 6º passo: Previsto acumulado do mês | F35: 0.9706
B37: 7º passo: Executado acumulado do mês | F37: 0.9584
B39: 8º passo: Crédito do orçamento (executado acumulado × orçamento) | F39: =F37*J28 -> 21457311
B41: 8º passo (cont.): Saldo de contrato (tabela) | F41: =E74 -> 0
B43: 9º passo: Adiantamento de serviços não medidos (tabela) | F43: =E88 -> 0
B45: 10º passo: Adiantamento de materiais não estocados (tabela) | F45: =J74 -> 0
B47: 11º passo: Estoque de materiais (almoxarifado) | F47: =J88 -> 237201.62
B49: 12º passo: Equipamentos comprados (valor de mercado) | F49: =E102 -> 183300
B51: 13º passo: Receitas de personalizações (tabela) | F51: =J102 -> 574500
B53: 14º passo: Contas a pagar dos medidos (relatório a pagar) | F53: =E115 -> 72903.09
B55: 15º passo: Valor desembolsado pela obra (relatório conferido) | F55: 21872066
B56: Valor corrigido (sem os itens apontados irregularmente) | F56: =F55-J115 -> 21872066
B58: 16º passo: Dívida da obra a ser paga (outra obra da carteira) | F58: =E129 -> 0
B63: Saldo de contrato | G63: Adiantamento de materiais não estocados
B74: Total | E74: =SUM(E64:E73) -> 0 | G74: Total | J74: =SUM(J64:J73) -> 0
B77: Adiantamento de serviços não medidos | G77: Estoque de materiais
G78: Revestimento cerâmico interno | J78: 32084.76
G79: Porcelanato das áreas comuns | J79: 46198.98
G80: Louças e metais | J80: 50591.58
G81: Material elétrico (fios e cabos) | J81: 29720.6
G82: Tinta acrílica | J82: 42141.89
G83: Material para impermeabilização | J83: 36463.81
B88: Total | E88: =SUM(E78:E87) -> 0 | G88: Total | J88: =SUM(J78:J87) -> 237201.62
B91: Equipamentos comprados | G91: Receitas de personalizações
B92: Betoneira 400 L | E92: 9800 | G92: Unid. 501 · troca de piso da sala (cliente I. Moura) | J92: 88424.28
B93: Guincho de coluna | E93: 38500 | G93: Unid. 1603 · bancada da cozinha em quartzo (cliente J. Viana) | J93: 79999.9
B94: Andaime fachadeiro (lote) | E94: 64000 | G94: Unid. 401 · planta com home office (cliente K. Saraiva) | J94: 89956.48
B95: Plataforma elevatória | E95: 71000 | G95: Unid. 201 · ponto extra de ar-condicionado (cliente L. Fernandes) | J95: 72661.9
G96: Unid. 302 · revestimento da varanda (cliente M. Albuquerque) | J96: 60748.78
G97: Unid. 1302 · fechamento da cozinha (cliente N. Siqueira) | J97: 80013.46
G98: Unid. 1104 · box e metais de padrão superior (cliente A. Cavalcanti) | J98: 102695.2
B102: Total | E102: =SUM(E92:E101) -> 183300 | G102: Total | J102: =SUM(J92:J101) -> 574500
B105: Contas a pagar dos medidos | G105: Itens apontados irregularmente no relatório
B106: Medição de reboco e gesso · NF 54007 | E106: 13989.41
B107: Medição de pintura · NF 95391 | E107: 17175.79
B108: Medição de revestimento · NF 14367 | E108: 14008.94
B109: Medição de instalações elétricas · NF 41969 | E109: 16091.5
B110: Encargos e INSS do mês · NF 8963 | E110: 11637.45
B115: Total | E115: =SUM(E106:E114) -> 72903.09 | G115: Total | J115: =SUM(J106:J114) -> 0
B118: Dívida da obra a ser paga
B129: Total | E129: =SUM(E119:E128) -> 0
B132: RESULTADO PARA UTILIZAR NA APRESENTAÇÃO
G135: Tabela informativa do desembolso do mês
C136: Projeto | D136: =D24 -> CAJUEIRO | G136: Valor previsto para o mês | J136: 586750.82
C137: Orçamento | D137: =J28 -> 22388680 | G137: Valor desembolsado no mês | J137: 581893.49
C138: Tipo do orçamento | D138: =J29 -> Orçamento final | G138: Diferença entre o previsto e o desembolsado | J138: =J137-J136 -> -4857.33
C139: Mês | D139: =E26 -> 46235 | G139: Justificativa para diferença acima de 10% (obrigatória)
C140: % previsto do mês | D140: =F31 -> 0.0157
C141: % executado do mês | D141: =F33 -> 0.0202
C142: % previsto acumulado | D142: =F35 -> 0.9706
C143: % executado acumulado | D143: =F37 -> 0.9584
B145: 01 | C145: Crédito do orçamento | D145: =F39 -> 21457311 | E145: =D145/$D$137 -> 0.9584
B146: 02 | C146: Saldo de contrato | D146: =F41 -> 0 | E146: =D146/$D$137 -> 0
B147: 03 | C147: Adiantamento de serviços não medidos | D147: =F43 -> 0 | E147: =D147/$D$137 -> 0
B148: 04 | C148: Adiantamento de materiais não estocados | D148: =F45 -> 0 | E148: =D148/$D$137 -> 0
B149: 05 | C149: Estoque de materiais | D149: =F47 -> 237201.62 | E149: =D149/$D$137 -> 0.010594712
B150: 06 | C150: Equipamentos (valor de mercado) | D150: =F49 -> 183300 | E150: =D150/$D$137 -> 0.0081871732
B151: 07 | C151: Receita de personalizações | D151: =F51 -> 574500 | E151: =D151/$D$137 -> 0.025660289
B152: 08 | C152: Contas a pagar dos medidos | D152: =F53 -> 72903.09 | E152: =D152/$D$137 -> 0.0032562478
B153: 09 | C153: Valor desembolsado (corrigido) | D153: =F56 -> 21872066 | E153: =D153/$D$137 -> 0.97692521
B154: 10 | C154: Dívida da obra a ser paga | D154: =F58 -> 0 | E154: =D154/$D$137 -> 0
C155: Resultado mensal da obra | D155: =D145+D146+D147+D148+D149+D150+D151-D152-D153-D154 -> 507343.43 | E155: =D155/D137 -> 0.022660712
C156: Resultado do mês anterior | D156: =JUL26!D155 -> 506002.5 | E156: =JUL26!E155 -> 0.022691916
B160: Significado de cada item
B162: Crédito do orçamento:
B163: Quanto a obra podia ter gasto pelo que executou: orçamento × executado acumulado.
B164: Saldo de contrato:
B165: Desconto obtido num contrato e ainda não realizado; abatido à medida que o serviço é medido.
B166: Adiantamento de serviços não medidos:
B167: Sinal pago de contrato ainda não medido (ex.: elevadores).
B168: Adiantamento de materiais não estocados:
B169: Material pago que ainda não chegou à obra (ex.: esquadrias).
B170: Estoque de materiais:
B171: Material no almoxarifado, ainda não aplicado, informado pelo almoxarife.
B172: Equipamentos (valor de mercado):
... B181: Material de outra obra da carteira usado nesta: custo da obra, desconta do resultado (versão 01 da planilha).

Sheet SET26
B2: ANÁLISE DE DESEMPENHO ECONÔMICO DA OBRA
B3: Construtora fictícia de Natal/RN · portfólio Vizu Dados · dados inventados
B4: Versão 01 · revisão de 01/09/2025: a dívida da obra passa a descontar do resultado
B18: Célula editável
B19: Resultado (não editar)
B20: Tabela anexada
B21: % relacionada
B24: 1º passo: Projeto (definir o empreendimento) | D24: CAJUEIRO
B26: 2º passo: Mês de análise (definir o mês de referência) | E26: 46266
B28: 3º passo: Orçamento da obra projetado (com INCC no a realizar) | J28: 22478560
B29: Tipo do orçamento | J29: Orçamento final
B31: 4º passo: Previsto do mês (incluir o % do cronograma) | F31: 0.0126
B33: 5º passo: Executado do mês (incluir o % medido) | F33: 0.0159
B35: 6º passo: Previsto acumulado do mês | F35: 0.9832
B37: 7º passo: Executado acumulado do mês | F37: 0.9743
B39: 8º passo: Crédito do orçamento (executado acumulado × orçamento) | F39: =F37*J28 -> 21900861
B41: 8º passo (cont.): Saldo de contrato (tabela) | F41: =E74 -> 0
B43: 9º passo: Adiantamento de serviços não medidos (tabela) | F43: =E88 -> 0
B45: 10º passo: Adiantamento de materiais não estocados (tabela) | F45: =J74 -> 0
B47: 11º passo: Estoque de materiais (almoxarifado) | F47: =J88 -> 52715.27
B49: 12º passo: Equipamentos comprados (valor de mercado) | F49: =E102 -> 183300
B51: 13º passo: Receitas de personalizações (tabela) | F51: =J102 -> 592000
B53: 14º passo: Contas a pagar dos medidos (relatório a pagar) | F53: =E115 -> 83526.48
B55: 15º passo: Valor desembolsado pela obra (relatório conferido) | F55: 22138392
B56: Valor corrigido (sem os itens apontados irregularmente) | F56: =F55-J115 -> 22138392
B58: 16º passo: Dívida da obra a ser paga (outra obra da carteira) | F58: =E129 -> 0
B63: Saldo de contrato | G63: Adiantamento de materiais não estocados
B74: Total | E74: =SUM(E64:E73) -> 0 | G74: Total | J74: =SUM(J64:J73) -> 0
B77: Adiantamento de serviços não medidos | G77: Estoque de materiais
G78: Louças e metais de reposição | J78: 32865.15
G79: Tinta para retoques | J79: 19850.12
B88: Total | E88: =SUM(E78:E87) -> 0 | G88: Total | J88: =SUM(J78:J87) -> 52715.27
B91: Equipamentos comprados | G91: Receitas de personalizações
B92: Betoneira 400 L | E92: 9800 | G92: Unid. 501 · troca de piso da sala (cliente I. Moura) | J92: 75583
B93: Guincho de coluna | E93: 38500 | G93: Unid. 1603 · bancada da cozinha em quartzo (cliente J. Viana) | J93: 68382.04
B94: Andaime fachadeiro (lote) | E94: 64000 | G94: Unid. 401 · planta com home office (cliente K. Saraiva) | J94: 76892.69
B95: Plataforma elevatória | E95: 71000 | G95: Unid. 201 · ponto extra de ar-condicionado (cliente L. Fernandes) | J95: 62109.69
G96: Unid. 302 · revestimento da varanda (cliente M. Albuquerque) | J96: 51926.63
G97: Unid. 1302 · fechamento da cozinha (cliente N. Siqueira) | J97: 68393.62
G98: Unid. 1104 · box e metais de padrão superior (cliente A. Cavalcanti) | J98: 87781.44
G99: Unid. 801 · iluminação embutida (cliente B. Freire) | J99: 100930.89
B102: Total | E102: =SUM(E92:E101) -> 183300 | G102: Total | J102: =SUM(J92:J101) -> 592000
B105: Contas a pagar dos medidos | G105: Itens apontados irregularmente no relatório
B106: Medição de pintura final · NF 31874 | E106: 29896.75
B107: Limpeza final e entrega · NF 89518 | E107: 23944.43
B108: Encargos e INSS do mês · NF 9346 | E108: 29685.3
B115: Total | E115: =SUM(E106:E114) -> 83526.48 | G115: Total | J115: =SUM(J106:J114) -> 0
B118: Dívida da obra a ser paga
B129: Total | E129: =SUM(E119:E128) -> 0
B132: RESULTADO PARA UTILIZAR NA APRESENTAÇÃO
G135: Tabela informativa do desembolso do mês
C136: Projeto | D136: =D24 -> CAJUEIRO | G136: Valor previsto para o mês | J136: 280910.91
C137: Orçamento | D137: =J28 -> 22478560 | G137: Valor desembolsado no mês | J137: 266325.75
C138: Tipo do orçamento | D138: =J29 -> Orçamento final | G138: Diferença entre o previsto e o desembolsado | J138: =J137-J136 -> -14585.16
C139: Mês | D139: =E26 -> 46266 | G139: Justificativa para diferença acima de 10% (obrigatória)
C140: % previsto do mês | D140: =F31 -> 0.0126
C141: % executado do mês | D141: =F33 -> 0.0159
C142: % previsto acumulado | D142: =F35 -> 0.9832
C143: % executado acumulado | D143: =F37 -> 0.9743
B145: 01 | C145: Crédito do orçamento | D145: =F39 -> 21900861 | E145: =D145/$D$137 -> 0.9743
B146: 02 | C146: Saldo de contrato | D146: =F41 -> 0 | E146: =D146/$D$137 -> 0
B147: 03 | C147: Adiantamento de serviços não medidos | D147: =F43 -> 0 | E147: =D147/$D$137 -> 0
B148: 04 | C148: Adiantamento de materiais não estocados | D148: =F45 -> 0 | E148: =D148/$D$137 -> 0
B149: 05 | C149: Estoque de materiais | D149: =F47 -> 52715.27 | E149: =D149/$D$137 -> 0.0023451355
B150: 06 | C150: Equipamentos (valor de mercado) | D150: =F49 -> 183300 | E150: =D150/$D$137 -> 0.0081544369
B151: 07 | C151: Receita de personalizações | D151: =F51 -> 592000 | E151: =D151/$D$137 -> 0.026336207
B152: 08 | C152: Contas a pagar dos medidos | D152: =F53 -> 83526.48 | E152: =D152/$D$137 -> 0.0037158288
B153: 09 | C153: Valor desembolsado (corrigido) | D153: =F56 -> 22138392 | E153: =D153/$D$137 -> 0.98486699
B154: 10 | C154: Dívida da obra a ser paga | D154: =F58 -> 0 | E154: =D154/$D$137 -> 0
C155: Resultado mensal da obra | D155: =D145+D146+D147+D148+D149+D150+D151-D152-D153-D154 -> 506958.04 | E155: =D155/D137 -> 0.022552959
C156: Resultado do mês anterior | D156: =AGO26!D155 -> 507343.43 | E156: =AGO26!E155 -> 0.022660712
B160: Significado de cada item
B162: Crédito do orçamento:
B163: Quanto a obra podia ter gasto pelo que executou: orçamento × executado acumulado.
B164: Saldo de contrato:
B165: Desconto obtido num contrato e ainda não realizado; abatido à medida que o serviço é medido.
B166: Adiantamento de serviços não medidos:
B167: Sinal pago de contrato ainda não medido (ex.: elevadores).
B168: Adiantamento de materiais não estocados:
B169: Material pago que ainda não chegou à obra (ex.: esquadrias).
B170: Estoque de materiais:
B171: Material no almoxarifado, ainda não aplicado, informado pelo almoxarife.
B172: Equipamentos (valor de mercado):
... B181: Material de outra obra da carteira usado nesta: custo da obra, desconta do resultado (versão 01 da planilha).
